{"ALA_ASM":["LEG_4453","LEG_4454","LEG_4455","LEG_4456"],"ALA_CTR":["LEG_4457"],"ALA_LFC":["LEG_4518","LEG_1677","LEG_117"],"ALA_MCY":["LEG_4460"],"ALA_MKD":["LEG_4461"],"ALA_NAT":["LEG_4518","LEG_1793","LEG_120"],"ALA_NEM":["LEG_4464"],"ALA_OTP":["LEG_4453","LEG_4465","LEG_4466","LEG_4467"],"ALA_PRK":["LEG_4468"],"ALA_SKG":["LEG_4518","LEG_1677","LEG_125"],"ALA_SMT":["LEG_4453","LEG_4454","LEG_4470"],"ALA_UOC":["LEG_4453","LEG_4454","LEG_4471","LEG_4472"],"ALA_VIC":["LEG_4473"],"ALA_ACOA":["LEG_1742"],"ALA_ASOC":["LEG_4475"],"ALA_ASOM":["LEG_4476"],"ALA_AOAC":["LEG_4477"],"ALA_BCOA":["LEG_4478"],"ALA_BVNA":["LEG_4479"],"ALA_BVNC":["LEG_4480"],"ALA_BBTC":["LEG_4481"],"ALA_CFCS":["LEG_4482"],"ALA_MPFT":["LEG_4483"],"ALA_CIOR":["LEG_4484"],"ALA_CMGM":["LEG_4485"],"ALA_MWZB":["LEG_4486"],"ALA_XGNZ":["LEG_4487"],"ALA_ZPEB":["LEG_4488"],"ALA_YHST":["LEG_4489"],"ALA_NOBD":["LEG_4490"],"ALA_DCOA":["LEG_4491"],"ALA_ETCM":["LEG_4492"],"ALA_EKUE":["LEG_4493"],"ALA_YRMA":["LEG_4494"],"ALA_LYRX":["LEG_4495"],"ALA_HFCO":["LEG_4496"],"ALA_IMTT":["LEG_4497"],"ALA_LCOM":["LEG_4498"],"ALA_LETC":["LEG_4499"],"ALA_MKSH":["LEG_4500"],"ALA_GIWF":["LEG_4501"],"ALA_MICP":["LEG_4502"],"ALA_NAAS":["LEG_4503"],"ALA_NMAA":["LEG_4504"],"ALA_PFFE":["LEG_4505"],"ALA_RGMG":["LEG_4506"],"ALA_SKCM":["LEG_4507"],"ALA_MVKH":["LEG_4508"],"ALA_SCOT":["LEG_4509"],"ALA_SNCO":["LEG_4510"],"ALA_SRVG":["LEG_4511"],"ALA_TECO":["LEG_4512"],"ALA_TECE":["LEG_4513"],"ALA_QNNI":["LEG_4514"],"ALA_AIEB":["LEG_3711"],"ALA_VVCO":["LEG_4516"],"ALA_YIOM":["LEG_4517"],"ALA_AHMI":["LEG_112","LEG_1677","LEG_2877"],"ALA_AHAA":["LEG_112","LEG_476","LEG_2694"],"ALA_AAAS":["LEG_112","LEG_111","LEG_110"],"ALA_AIAA":["LEG_112","LEG_111","LEG_3178"],"ALA_AJAA":["LEG_4297"],"ALA_ASCO":["LEG_4520"],"ALA_AACN":["LEG_112","LEG_476","LEG_475"],"ALA_AACT":["LEG_112","LEG_986","LEG_985"],"ALA_QZSP":["LEG_4518","LEG_111","LEG_702"],"ALA_ACT":["LEG_112","LEG_111","LEG_2335"],"ALA_FITC":["LEG_4521"],"ALA_WCEK":["LEG_4522"],"ALA_AAMC":["LEG_1444"],"ALA_AACV":["LEG_112","LEG_1219","LEG_1218"],"ALA_ATCF":["LEG_4524"],"ALA_AWCP":["LEG_4525"],"ALA_AIAC":["LEG_112","LEG_111","LEG_3392"],"ALA_XRLI":["LEG_4518","LEG_111","LEG_711"],"ALA_AIWA":["LEG_112","LEG_986","LEG_4054"],"ALA_AIAT":["LEG_3555"],"ALA_AIFT":["LEG_3879"],"ALA_NMLY":["LEG_4518","LEG_688","LEG_149"],"ALA_AACP":["LEG_112","LEG_688","LEG_687"],"ALA_FWXK":["LEG_4518","LEG_688","LEG_151"],"ALA_ACOE":["LEG_4518","LEG_75724","LEG_75717"],"ALA_ACOS":["LEG_112","LEG_688","LEG_2103"],"ALA_ASCK":["LEG_4518","LEG_111","LEG_716"],"ALA_BCC":["LEG_4518","LEG_476","LEG_717"],"ALA_BYAA":["LEG_4518","LEG_1219","LEG_495"],"ALA_BIAC":["LEG_4518","LEG_111","LEG_719"],"ALA_BIAS":["LEG_4518","LEG_111","LEG_720"],"ALA_BIOM":["LEG_4518","LEG_1677","LEG_155"],"ALA_BRIO":["LEG_4518","LEG_111","LEG_721"],"ALA_BASC":["LEG_4518","LEG_986","LEG_499"],"ALA_BUAC":["LEG_4518","LEG_1677","LEG_161"],"ALA_CKRM":["LEG_4518","LEG_111","LEG_723"],"ALA_CMGC":["LEG_4518","LEG_476","LEG_724"],"ALA_CCOA":["LEG_4518","LEG_111","LEG_725"],"ALA_CURC":["LEG_4518","LEG_476","LEG_726"],"ALA_CCM":["LEG_4518","LEG_1677","LEG_164"],"ALA_MDWG":["LEG_4518","LEG_1677","LEG_166"],"ALA_BKCS":["LEG_4518","LEG_111","LEG_727"],"ALA_FNTR":["LEG_4518","LEG_1677","LEG_168"],"ALA_TEGU":["LEG_4518","LEG_1677","LEG_169"],"ALA_FIAQ":["LEG_4518","LEG_1677","LEG_170"],"ALA_UFHJ":["LEG_4518","LEG_1677","LEG_171"],"ALA_MCBJ":["LEG_4518","LEG_1219","LEG_503"],"ALA_PSUL":["LEG_4518","LEG_476","LEG_729"],"ALA_AQYX":["LEG_4518","LEG_688","LEG_174"],"ALA_ABCD":["LEG_112","LEG_1677","LEG_1676"],"ALA_CMKM":["LEG_4518","LEG_75723","LEG_75716"],"ALA_CCOS":["LEG_4528"],"ALA_CCOM":["LEG_4518","LEG_1677","LEG_180"],"ALA_CGAA":["LEG_4518","LEG_111","LEG_732"],"ALA_CCI":["LEG_4518","LEG_1793","LEG_181"],"ALA_CCOT":["LEG_4518","LEG_111","LEG_733"],"ALA_CAAS":["LEG_4518","LEG_476","LEG_734"],"ALA_COAS":["LEG_4529"],"ALA_PLCT":["LEG_4518","LEG_476","LEG_736"],"ALA_JWRH":["LEG_4518","LEG_111","LEG_737"],"ALA_VVFQ":["LEG_4518","LEG_1677","LEG_187"],"ALA_FKIA":["LEG_4518","LEG_111","LEG_738"],"ALA_VPGG":["LEG_4518","LEG_986","LEG_509"],"ALA_MHFR":["LEG_4518","LEG_1677","LEG_191"],"ALA_PELD":["LEG_4518","LEG_111","LEG_740"],"ALA_RLPO":["LEG_4518","LEG_688","LEG_193"],"ALA_FIEY":["LEG_4518","LEG_111","LEG_741"],"ALA_CRCF":["LEG_4518","LEG_111","LEG_742"],"ALA_CCOG":["LEG_4518","LEG_1219","LEG_513"],"ALA_CCMW":["LEG_4518","LEG_476","LEG_744"],"ALA_DMAC":["LEG_4518","LEG_111","LEG_745"],"ALA_SXMT":["LEG_4518","LEG_111","LEG_746"],"ALA_DUAC":["LEG_4518","LEG_111","LEG_747"],"ALA_DUTC":["LEG_4518","LEG_111","LEG_748"],"ALA_DAAS":["LEG_4518","LEG_111","LEG_749"],"ALA_DPIO":["LEG_4518","LEG_1219","LEG_519"],"ALA_DAMC":["LEG_4518","LEG_986","LEG_520"],"ALA_TXFN":["LEG_4518","LEG_986","LEG_521"],"ALA_KWHT":["LEG_4518","LEG_476","LEG_753"],"ALA_DIOM":["LEG_4518","LEG_75772","LEG_75770"],"ALA_DBCM":["LEG_4518","LEG_111","LEG_754"],"ALA_JPIH":["LEG_4518","LEG_1677","LEG_202"],"ALA_DBCS":["LEG_4518","LEG_111","LEG_755"],"ALA_DPMS":["LEG_4518","LEG_1677","LEG_203"],"ALA_DAMG":["LEG_4518","LEG_111","LEG_756"],"ALA_DCFA":["LEG_4518","LEG_1219","LEG_525"],"ALA_ECOA":["LEG_4518","LEG_986","LEG_526"],"ALA_EAAS":["LEG_4518","LEG_476","LEG_759"],"ALA_EMBC":["LEG_4518","LEG_111","LEG_760"],"ALA_EIOM":["LEG_4518","LEG_1677","LEG_207"],"ALA_CCXH":["LEG_4518","LEG_1677","LEG_208"],"ALA_EKCC":["LEG_4518","LEG_1219","LEG_528"],"ALA_ECFA":["LEG_4518","LEG_1219","LEG_529"],"ALA_ETCI":["LEG_4518","LEG_1793","LEG_211"],"ALA_FACD":["LEG_4518","LEG_1219","LEG_530"],"ALA_FBCC":["LEG_4518","LEG_1219","LEG_531"],"ALA_FCK":["LEG_4518","LEG_75724","LEG_75718"],"ALA_FIOM":["LEG_4518","LEG_75724","LEG_75719"],"ALA_FTCF":["LEG_4518","LEG_75724","LEG_75720"],"ALA_FAAS":["LEG_4530"],"ALA_GAAS":["LEG_4518","LEG_1219","LEG_535"],"ALA_GHAA":["LEG_4518","LEG_111","LEG_770"],"ALA_GCKK":["LEG_4518","LEG_111","LEG_771"],"ALA_GASC":["LEG_4531"],"ALA_GCM":["LEG_4518","LEG_1219","LEG_538"],"ALA_RCTY":["LEG_4518","LEG_1219","LEG_539"],"ALA_EVZE":["LEG_4518","LEG_986","LEG_540"],"ALA_CBRK":["LEG_4518","LEG_111","LEG_776"],"ALA_KAIN":["LEG_4532"],"ALA_XOGR":["LEG_4518","LEG_476","LEG_778"],"ALA_WUTE":["LEG_4518","LEG_476","LEG_779"],"ALA_IODZ":["LEG_4518","LEG_476","LEG_780"],"ALA_BMSE":["LEG_4518","LEG_1677","LEG_226"],"ALA_PCSZ":["LEG_4518","LEG_688","LEG_228"],"ALA_ALOU":["LEG_4518","LEG_688","LEG_229"],"ALA_GCOP":["LEG_4518","LEG_111","LEG_781"],"ALA_GCOT":["LEG_4518","LEG_111","LEG_782"],"ALA_YNGR":["LEG_4518","LEG_1219","LEG_544"],"ALA_GVCO":["LEG_4518","LEG_1219","LEG_545"],"ALA_GCOA":["LEG_4518","LEG_111","LEG_785"],"ALA_HGMW":["LEG_4518","LEG_1219","LEG_547"],"ALA_HAAS":["LEG_4518","LEG_476","LEG_787"],"ALA_HCOA":["LEG_4533"],"ALA_HMCO":["LEG_4518","LEG_1219","LEG_548"],"ALA_HPKC":["LEG_4518","LEG_1677","LEG_237"],"ALA_HCIO":["LEG_4518","LEG_111","LEG_790"],"ALA_HGAO":["LEG_4518","LEG_1677","LEG_239"],"ALA_XUJC":["LEG_4518","LEG_1677","LEG_240"],"ALA_IAAS":["LEG_4534"],"ALA_ICFA":["LEG_4518","LEG_688","LEG_242"],"ALA_ICOA":["LEG_4518","LEG_476","LEG_792"],"ALA_ITCP":["LEG_4535"],"ALA_JTTG":["LEG_4518","LEG_1677","LEG_245"],"ALA_IMAA":["LEG_4518","LEG_1219","LEG_550"],"ALA_IASC":["LEG_4518","LEG_111","LEG_795"],"ALA_LKLX":["LEG_4536"],"ALA_IOAS":["LEG_4518","LEG_1677","LEG_249"],"ALA_IIAC":["LEG_4518","LEG_986","LEG_552"],"ALA_XHDK":["LEG_4537"],"ALA_ICOT":["LEG_4538"],"ALA_ICSB":["LEG_4518","LEG_111","LEG_800"],"ALA_JWAC":["LEG_4518","LEG_111","LEG_801"],"ALA_JNAS":["LEG_4518","LEG_1219","LEG_555"],"ALA_JNTC":["LEG_4518","LEG_1219","LEG_556"],"ALA_JNWA":["LEG_4518","LEG_1219","LEG_557"],"ALA_JIAA":["LEG_4518","LEG_1219","LEG_558"],"ALA_JAAS":["LEG_4518","LEG_111","LEG_806"],"ALA_JICO":["LEG_4518","LEG_111","LEG_807"],"ALA_JTCM":["LEG_4518","LEG_1677","LEG_257"],"ALA_JCOA":["LEG_4518","LEG_1219","LEG_561"],"ALA_JTCK":["LEG_4518","LEG_1677","LEG_259"],"ALA_KMCO":["LEG_4518","LEG_111","LEG_809"],"ALA_KTMC":["LEG_4539"],"ALA_KPX":["LEG_4518","LEG_1677","LEG_261"],"ALA_KACT":["LEG_4518","LEG_986","LEG_563"],"ALA_KSCK":["LEG_4518","LEG_111","LEG_812"],"ALA_KUMD":["LEG_4518","LEG_688","LEG_263"],"ALA_KASC":["LEG_4518","LEG_476","LEG_813"],"ALA_KCAU":["LEG_4518","LEG_111","LEG_814"],"ALA_KPAT":["LEG_4518","LEG_1677","LEG_265"],"ALA_KCOT":["LEG_4518","LEG_111","LEG_815"],"ALA_FHDX":["LEG_4518","LEG_1219","LEG_567"],"ALA_KCOD":["LEG_4518","LEG_1677","LEG_267"],"ALA_KAAS":["LEG_4518","LEG_688","LEG_268"],"ALA_STEJ":["LEG_4518","LEG_111","LEG_817"],"ALA_KCOE":["LEG_4518","LEG_111","LEG_818"],"ALA_TMOV":["LEG_4518","LEG_111","LEG_819"],"ALA_KAHM":["LEG_4518","LEG_1219","LEG_571"],"ALA_KFAA":["LEG_4518","LEG_1219","LEG_572"],"ALA_EERX":["LEG_4518","LEG_1219","LEG_573"],"ALA_KSNC":["LEG_4518","LEG_688","LEG_272"],"ALA_VEKH":["LEG_4540"],"ALA_QHPR":["LEG_4518","LEG_111","LEG_824"],"ALA_KGAS":["LEG_4518","LEG_111","LEG_825"],"ALA_LNAA":["LEG_4541"],"ALA_LMDC":["LEG_4518","LEG_986","LEG_576"],"ALA_LCOA":["LEG_4542"],"ALA_LFIO":["LEG_4518","LEG_111","LEG_829"],"ALA_LAAS":["LEG_4518","LEG_688","LEG_280"],"ALA_MASC":["LEG_4518","LEG_111","LEG_830"],"ALA_SPGF":["LEG_4518","LEG_111","LEG_831"],"ALA_MAAS":["LEG_4518","LEG_688","LEG_281"],"ALA_QFGD":["LEG_4543"],"ALA_KNFJ":["LEG_4544"],"ALA_MCV":["LEG_4518","LEG_476","LEG_834"],"ALA_MKCV":["LEG_4518","LEG_688","LEG_286"],"ALA_MMC":["LEG_4545"],"ALA_MPC":["LEG_4518","LEG_688","LEG_288"],"ALA_MCOA":["LEG_4518","LEG_476","LEG_836"],"ALA_MTCP":["LEG_4518","LEG_688","LEG_290"],"ALA_MMSN":["LEG_4546"],"ALA_FCKE":["LEG_4547"],"ALA_NYDL":["LEG_4518","LEG_688","LEG_293"],"ALA_VASP":["LEG_4518","LEG_1219","LEG_581"],"ALA_MGIO":["LEG_4518","LEG_1219","LEG_582"],"ALA_MUAC":["LEG_4518","LEG_986","LEG_583"],"ALA_MTCM":["LEG_4548"],"ALA_QTRL":["LEG_4518","LEG_111","LEG_843"],"ALA_DBJV":["LEG_4518","LEG_688","LEG_298"],"ALA_YCOK":["LEG_4518","LEG_111","LEG_844"],"ALA_MTCR":["LEG_4518","LEG_111","LEG_845"],"ALA_XLQJ":["LEG_4518","LEG_476","LEG_846"],"ALA_MCCC":["LEG_4518","LEG_111","LEG_847"],"ALA_YOCB":["LEG_4518","LEG_1219","LEG_588"],"ALA_WGGT":["LEG_4518","LEG_111","LEG_849"],"ALA_MCOC":["LEG_4518","LEG_1219","LEG_590"],"ALA_JFLI":["LEG_4518","LEG_111","LEG_851"],"ALA_MBCO":["LEG_4518","LEG_111","LEG_852"],"ALA_MDCP":["LEG_4518","LEG_1677","LEG_302"],"ALA_MOCP":["LEG_4549"],"ALA_MOTC":["LEG_4550"],"ALA_WPEP":["LEG_4518","LEG_688","LEG_306"],"ALA_WDXW":["LEG_4518","LEG_111","LEG_855"],"ALA_MOCT":["LEG_4551"],"ALA_MTCA":["LEG_4518","LEG_688","LEG_308"],"ALA_MWWC":["LEG_4518","LEG_111","LEG_857"],"ALA_MCC":["LEG_4552"],"ALA_MAKA":["LEG_4518","LEG_1219","LEG_595"],"ALA_HIKB":["LEG_4518","LEG_1219","LEG_596"],"ALA_MSCO":["LEG_4518","LEG_476","LEG_861"],"ALA_MCOT":["LEG_4518","LEG_476","LEG_862"],"ALA_AHPE":["LEG_112","LEG_1677","LEG_3009"],"ALA_BECF":["LEG_4518","LEG_476","LEG_863"],"ALA_MCOS":["LEG_4518","LEG_476","LEG_864"],"ALA_SVBW":["LEG_4518","LEG_986","LEG_597"],"ALA_UKSD":["LEG_4518","LEG_688","LEG_318"],"ALA_MCM":["LEG_4518","LEG_111","LEG_866"],"ALA_MIIO":["LEG_4553"],"ALA_SSLJ":["LEG_4518","LEG_476","LEG_868"],"ALA_RPIU":["LEG_4518","LEG_1677","LEG_322"],"ALA_MTCO":["LEG_4518","LEG_476","LEG_869"],"ALA_YVQG":["LEG_4518","LEG_1219","LEG_599"],"ALA_LXAJ":["LEG_4518","LEG_1219","LEG_600"],"ALA_RCNF":["LEG_4554"],"ALA_MARM":["LEG_4518","LEG_111","LEG_873"],"ALA_MOCO":["LEG_4518","LEG_111","LEG_874"],"ALA_NGCK":["LEG_4518","LEG_111","LEG_875"],"ALA_NCM":["LEG_4518","LEG_1219","LEG_604"],"ALA_NBSK":["LEG_4518","LEG_1677","LEG_328"],"ALA_NIOM":["LEG_4518","LEG_1677","LEG_329"],"ALA_NCOS":["LEG_4555"],"ALA_NCOT":["LEG_4518","LEG_1677","LEG_332"],"ALA_NCOA":["LEG_4556"],"ALA_YBKE":["LEG_4518","LEG_476","LEG_879"],"ALA_NESA":["LEG_4518","LEG_1677","LEG_335"],"ALA_OMYK":["LEG_4518","LEG_1677","LEG_336"],"ALA_QLBF":["LEG_4518","LEG_75772","LEG_75766"],"ALA_NWCM":["LEG_4518","LEG_1219","LEG_605"],"ALA_JNZP":["LEG_4518","LEG_688","LEG_340"],"ALA_NTC":["LEG_4557"],"ALA_PYDS":["LEG_4558"],"ALA_OCOH":["LEG_4518","LEG_111","LEG_883"],"ALA_OCOT":["LEG_4518","LEG_111","LEG_884"],"ALA_OSOH":["LEG_4518","LEG_111","LEG_885"],"ALA_PVSC":["LEG_4518","LEG_111","LEG_886"],"ALA_PMST":["LEG_4518","LEG_986","LEG_610"],"ALA_PPTM":["LEG_4518","LEG_986","LEG_611"],"ALA_PMGC":["LEG_4518","LEG_75772","LEG_75767"],"ALA_PCOA":["LEG_4518","LEG_1677","LEG_346"],"ALA_PRCP":["LEG_4518","LEG_111","LEG_889"],"ALA_PCAA":["LEG_4518","LEG_111","LEG_890"],"ALA_PDLC":["LEG_4559"],"ALA_PSMO":["LEG_4518","LEG_986","LEG_614"],"ALA_PTMG":["LEG_4560"],"ALA_PMHT":["LEG_4518","LEG_1677","LEG_350"],"ALA_PNCP":["LEG_4518","LEG_1677","LEG_351"],"ALA_PAAS":["LEG_4518","LEG_688","LEG_352"],"ALA_PVCO":["LEG_4518","LEG_1219","LEG_615"],"ALA_PASC":["LEG_4518","LEG_1219","LEG_616"],"ALA_PCOT":["LEG_4518","LEG_111","LEG_896"],"ALA_PWCM":["LEG_4518","LEG_111","LEG_897"],"ALA_RMSY":["LEG_4518","LEG_111","LEG_898"],"ALA_RACK":["LEG_4518","LEG_476","LEG_899"],"ALA_RCOS":["LEG_4518","LEG_986","LEG_620"],"ALA_RUAC":["LEG_4518","LEG_75724","LEG_75721"],"ALA_WHEU":["LEG_4518","LEG_75724","LEG_75722"],"ALA_RCOA":["LEG_4518","LEG_688","LEG_359"],"ALA_SAAS":["LEG_4518","LEG_476","LEG_903"],"ALA_SYMR":["LEG_4518","LEG_111","LEG_904"],"ALA_SHCF":["LEG_4518","LEG_75772","LEG_75768"],"ALA_SACP":["LEG_4518","LEG_688","LEG_363"],"ALA_SCOA":["LEG_4518","LEG_688","LEG_364"],"ALA_SIOA":["LEG_4518","LEG_111","LEG_905"],"ALA_JCLJ":["LEG_4518","LEG_1677","LEG_365"],"ALA_SIOM":["LEG_4518","LEG_1677","LEG_366"],"ALA_SPZS":["LEG_4561"],"ALA_SACK":["LEG_4562"],"ALA_SACM":["LEG_4518","LEG_476","LEG_908"],"ALA_SCWK":["LEG_4563"],"ALA_STCK":["LEG_4564"],"ALA_SEOT":["LEG_4518","LEG_476","LEG_911"],"ALA_SIAC":["LEG_4518","LEG_476","LEG_912"],"ALA_SDSM":["LEG_4518","LEG_111","LEG_913"],"ALA_SMAS":["LEG_4518","LEG_688","LEG_374"],"ALA_SASC":["LEG_4518","LEG_1677","LEG_375"],"ALA_SODA":["LEG_4518","LEG_1677","LEG_376"],"ALA_MBQF":["LEG_4518","LEG_111","LEG_914"],"ALA_PEMA":["LEG_4518","LEG_688","LEG_377"],"ALA_TASU":["LEG_4518","LEG_476","LEG_915"],"ALA_WTSR":["LEG_4518","LEG_1677","LEG_380"],"ALA_LGNA":["LEG_4565"],"ALA_SCFW":["LEG_4518","LEG_986","LEG_627"],"ALA_QFIP":["LEG_4518","LEG_476","LEG_918"],"ALA_SHAS":["LEG_4518","LEG_476","LEG_919"],"ALA_SHIO":["LEG_4518","LEG_476","LEG_920"],"ALA_SYSS":["LEG_4566"],"ALA_AEUZ":["LEG_112","LEG_111","LEG_2549"],"ALA_WIUZ":["LEG_4518","LEG_111","LEG_923"],"ALA_SGAA":["LEG_4518","LEG_1677","LEG_388"],"ALA_MEWQ":["LEG_4518","LEG_111","LEG_924"],"ALA_SKCT":["LEG_4518","LEG_1677","LEG_389"],"ALA_SKVB":["LEG_4567"],"ALA_BFMH":["LEG_4518","LEG_111","LEG_926"],"ALA_SFLH":["LEG_4568"],"ALA_SNCV":["LEG_4518","LEG_476","LEG_928"],"ALA_DLGH":["LEG_4518","LEG_111","LEG_929"],"ALA_YANP":["LEG_4518","LEG_1677","LEG_394"],"ALA_SNCC":["LEG_4518","LEG_111","LEG_930"],"ALA_SNGS":["LEG_4453","LEG_4465","LEG_4569","LEG_4570","LEG_4571"],"ALA_SSCE":["LEG_4518","LEG_1219","LEG_634"],"ALA_SSVC":["LEG_4572"],"ALA_SVCO":["LEG_4573"],"ALA_SVCK":["LEG_4518","LEG_1677","LEG_400"],"ALA_SVPK":["LEG_4574"],"ALA_SVTE":["LEG_4518","LEG_1677","LEG_402"],"ALA_SVNC":["LEG_4575"],"ALA_JDNC":["LEG_4518","LEG_688","LEG_404"],"ALA_SSSS":["LEG_4518","LEG_476","LEG_937"],"ALA_SCGC":["LEG_4518","LEG_1677","LEG_406"],"ALA_KSQV":["LEG_4518","LEG_111","LEG_938"],"ALA_SACE":["LEG_4518","LEG_1677","LEG_407"],"ALA_SJCD":["LEG_4518","LEG_111","LEG_939"],"ALA_SJCI":["LEG_4518","LEG_1793","LEG_408"],"ALA_SMCP":["LEG_4576"],"ALA_SMCS":["LEG_4518","LEG_111","LEG_941"],"ALA_STAA":["LEG_4518","LEG_1677","LEG_410"],"ALA_SXAA":["LEG_4518","LEG_111","LEG_942"],"ALA_SBCP":["LEG_4518","LEG_476","LEG_943"],"ALA_SJAA":["LEG_4518","LEG_1677","LEG_412"],"ALA_SJTC":["LEG_4518","LEG_1677","LEG_413"],"ALA_STTC":["LEG_4518","LEG_111","LEG_944"],"ALA_SCT":["LEG_4518","LEG_1677","LEG_414"],"ALA_SACA":["LEG_4518","LEG_111","LEG_945"],"ALA_FDJM":["LEG_4518","LEG_111","LEG_946"],"ALA_SSCA":["LEG_4518","LEG_111","LEG_947"],"ALA_SACC":["LEG_4518","LEG_111","LEG_948"],"ALA_TQJV":["LEG_4518","LEG_111","LEG_949"],"ALA_SARB":["LEG_4518","LEG_111","LEG_950"],"ALA_TTCN":["LEG_4518","LEG_476","LEG_951"],"ALA_TAAC":["LEG_4518","LEG_688","LEG_416"],"ALA_TAAS":["LEG_4518","LEG_1677","LEG_417"],"ALA_TMGT":["LEG_4518","LEG_1219","LEG_646"],"ALA_UCOA":["LEG_4518","LEG_1677","LEG_421"],"ALA_UCFP":["LEG_4518","LEG_111","LEG_953"],"ALA_UTEC":["LEG_4518","LEG_75772","LEG_75769"],"ALA_QAAW":["LEG_4518","LEG_111","LEG_954"],"ALA_ROHW":["LEG_4518","LEG_986","LEG_649"],"ALA_BNSK":["LEG_4518","LEG_1677","LEG_425"],"ALA_EFYF":["LEG_4518","LEG_1219","LEG_650"],"ALA_VPRO":["LEG_4518","LEG_111","LEG_957"],"ALA_GBEQ":["LEG_4518","LEG_476","LEG_958"],"ALA_NWSW":["LEG_4518","LEG_1677","LEG_429"],"ALA_GOPO":["LEG_4518","LEG_111","LEG_959"],"ALA_VKHM":["LEG_4518","LEG_111","LEG_960"],"ALA_VPEC":["LEG_4577"],"ALA_VCOA":["LEG_4518","LEG_111","LEG_962"],"ALA_VCT":["LEG_4518","LEG_1677","LEG_432"],"ALA_WSCM":["LEG_4518","LEG_111","LEG_963"],"ALA_WAAS":["LEG_4578"],"ALA_ZGCC":["LEG_4518","LEG_111","LEG_965"]}