{"CIOR_ALA":["LEG_76975"],"CIOR_CTR":["LEG_11188"],"CIOR_MCY":["LEG_11189"],"CIOR_MKD":["LEG_11190"],"CIOR_NEM":["LEG_11191"],"CIOR_PRK":["LEG_11192"],"CIOR_VIC":["LEG_11193"],"CIOR_ACOA":["LEG_76455"],"CIOR_ASOC":["LEG_77216"],"CIOR_ASOM":["LEG_77227"],"CIOR_AOAC":["LEG_77027"],"CIOR_BCOA":["LEG_77330"],"CIOR_BVNA":["LEG_77843"],"CIOR_BVNC":["LEG_77859"],"CIOR_BBTC":["LEG_77278"],"CIOR_CFCS":["LEG_78308"],"CIOR_MPFT":["LEG_11203"],"CIOR_CMGM":["LEG_11204"],"CIOR_MWZB":["LEG_11205"],"CIOR_XGNZ":["LEG_11206"],"CIOR_ZPEB":["LEG_11207"],"CIOR_YHST":["LEG_11208"],"CIOR_NOBD":["LEG_11209"],"CIOR_DCOA":["LEG_11210"],"CIOR_ETCM":["LEG_11211"],"CIOR_EKUE":["LEG_11212"],"CIOR_YRMA":["LEG_11213"],"CIOR_LYRX":["LEG_11214"],"CIOR_HFCO":["LEG_11215"],"CIOR_IMTT":["LEG_11216"],"CIOR_LCOM":["LEG_11217"],"CIOR_LETC":["LEG_11218"],"CIOR_MKSH":["LEG_11219"],"CIOR_GIWF":["LEG_11220"],"CIOR_MICP":["LEG_11221"],"CIOR_NAAS":["LEG_11222"],"CIOR_NMAA":["LEG_11223"],"CIOR_PFFE":["LEG_11224"],"CIOR_RGMG":["LEG_11225"],"CIOR_SKCM":["LEG_11226"],"CIOR_MVKH":["LEG_11227"],"CIOR_SCOT":["LEG_11228"],"CIOR_SNCO":["LEG_11229"],"CIOR_SRVG":["LEG_11230"],"CIOR_TECO":["LEG_11231"],"CIOR_TECE":["LEG_11232"],"CIOR_QNNI":["LEG_11233"],"CIOR_AIEB":["LEG_76855"],"CIOR_VVCO":["LEG_11235"],"CIOR_YIOM":["LEG_11236"],"CIOR_ASM":["LEG_75904","LEG_1793","LEG_77169"],"CIOR_LFC":["LEG_11237","LEG_1794","LEG_117"],"CIOR_NAT":["LEG_11237","LEG_1793","LEG_120"],"CIOR_OTP":["LEG_11238"],"CIOR_SKG":["LEG_11237","LEG_1794","LEG_125"],"CIOR_SMT":["LEG_11237","LEG_1794","LEG_126"],"CIOR_UOC":["LEG_11237","LEG_1796","LEG_481"],"CIOR_AHMI":["LEG_75904","LEG_1794","LEG_76727"],"CIOR_AHAA":["LEG_75904","LEG_1797","LEG_76669"],"CIOR_AAAS":["LEG_75904","LEG_1798","LEG_75857"],"CIOR_AIAA":["LEG_75904","LEG_1798","LEG_76800"],"CIOR_AJAA":["LEG_11239"],"CIOR_ASCO":["LEG_11240"],"CIOR_AACN":["LEG_75904","LEG_1797","LEG_76080"],"CIOR_AACT":["LEG_75904","LEG_1796","LEG_76334"],"CIOR_QZSP":["LEG_11237","LEG_1798","LEG_702"],"CIOR_ACT":["LEG_75904","LEG_1798","LEG_76630"],"CIOR_FITC":["LEG_11241"],"CIOR_WCEK":["LEG_11242"],"CIOR_AAMC":["LEG_11243"],"CIOR_AACV":["LEG_75904","LEG_1804","LEG_76364"],"CIOR_ATCF":["LEG_11244"],"CIOR_AWCP":["LEG_11245"],"CIOR_AIAC":["LEG_75904","LEG_1798","LEG_76838"],"CIOR_XRLI":["LEG_11237","LEG_1798","LEG_711"],"CIOR_AIWA":["LEG_75904","LEG_1796","LEG_76896"],"CIOR_AIAT":["LEG_11246"],"CIOR_AIFT":["LEG_11247"],"CIOR_NMLY":["LEG_11237","LEG_1809","LEG_149"],"CIOR_AACP":["LEG_75904","LEG_1809","LEG_76174"],"CIOR_FWXK":["LEG_11237","LEG_1809","LEG_151"],"CIOR_ACOE":["LEG_75904","LEG_83698","LEG_83664"],"CIOR_ACOS":["LEG_75904","LEG_1809","LEG_76576"],"CIOR_ASCK":["LEG_75904","LEG_1798","LEG_77160"],"CIOR_BCC":["LEG_75904","LEG_1797","LEG_77321"],"CIOR_BYAA":["LEG_75904","LEG_1804","LEG_77904"],"CIOR_BIAC":["LEG_75904","LEG_1798","LEG_77480"],"CIOR_BIAS":["LEG_75904","LEG_1798","LEG_77508"],"CIOR_BIOM":["LEG_75904","LEG_1794","LEG_77561"],"CIOR_BRIO":["LEG_75904","LEG_1798","LEG_77788"],"CIOR_BASC":["LEG_75904","LEG_1796","LEG_77266"],"CIOR_BUAC":["LEG_75904","LEG_1794","LEG_77841"],"CIOR_CKRM":["LEG_11237","LEG_1798","LEG_723"],"CIOR_CMGC":["LEG_11237","LEG_1797","LEG_724"],"CIOR_CCOA":["LEG_75904","LEG_1798","LEG_78089"],"CIOR_CURC":["LEG_11237","LEG_1797","LEG_726"],"CIOR_CCM":["LEG_75904","LEG_1794","LEG_78030"],"CIOR_MDWG":["LEG_11237","LEG_1794","LEG_166"],"CIOR_BKCS":["LEG_75904","LEG_1798","LEG_77596"],"CIOR_FNTR":["LEG_11237","LEG_1794","LEG_168"],"CIOR_TEGU":["LEG_11237","LEG_1794","LEG_169"],"CIOR_FIAQ":["LEG_11237","LEG_1794","LEG_170"],"CIOR_UFHJ":["LEG_11237","LEG_1794","LEG_171"],"CIOR_MCBJ":["LEG_11237","LEG_1804","LEG_503"],"CIOR_PSUL":["LEG_11237","LEG_1797","LEG_729"],"CIOR_AQYX":["LEG_75904","LEG_1809","LEG_77064"],"CIOR_ABCD":["LEG_75904","LEG_1794","LEG_76447"],"CIOR_CMKM":["LEG_75904","LEG_83697","LEG_83662"],"CIOR_CCOS":["LEG_11248"],"CIOR_CCOM":["LEG_75904","LEG_1794","LEG_78178"],"CIOR_CGAA":["LEG_75904","LEG_1798","LEG_78344"],"CIOR_CCI":["LEG_75904","LEG_1793","LEG_77988"],"CIOR_CCOT":["LEG_75904","LEG_1798","LEG_78253"],"CIOR_CAAS":["LEG_75904","LEG_1797","LEG_77912"],"CIOR_COAS":["LEG_11249"],"CIOR_PLCT":["LEG_11237","LEG_1797","LEG_736"],"CIOR_JWRH":["LEG_11237","LEG_1798","LEG_737"],"CIOR_VVFQ":["LEG_11237","LEG_1794","LEG_187"],"CIOR_FKIA":["LEG_11237","LEG_1798","LEG_738"],"CIOR_VPGG":["LEG_11237","LEG_1796","LEG_509"],"CIOR_MHFR":["LEG_11237","LEG_1794","LEG_191"],"CIOR_PELD":["LEG_11237","LEG_1798","LEG_740"],"CIOR_RLPO":["LEG_11237","LEG_1809","LEG_193"],"CIOR_FIEY":["LEG_11237","LEG_1798","LEG_741"],"CIOR_CRCF":["LEG_11237","LEG_1798","LEG_742"],"CIOR_CCOG":["LEG_75904","LEG_1804","LEG_78130"],"CIOR_CCMW":["LEG_75904","LEG_1797","LEG_78031"],"CIOR_DMAC":["LEG_11237","LEG_1798","LEG_745"],"CIOR_SXMT":["LEG_11237","LEG_1798","LEG_746"],"CIOR_DUAC":["LEG_11237","LEG_1798","LEG_747"],"CIOR_DUTC":["LEG_11237","LEG_1798","LEG_748"],"CIOR_DAAS":["LEG_11237","LEG_1798","LEG_749"],"CIOR_DPIO":["LEG_11237","LEG_1804","LEG_519"],"CIOR_DAMC":["LEG_11237","LEG_1796","LEG_520"],"CIOR_TXFN":["LEG_11237","LEG_1796","LEG_521"],"CIOR_KWHT":["LEG_11237","LEG_1797","LEG_753"],"CIOR_DIOM":["LEG_11237","LEG_1794","LEG_201"],"CIOR_DBCM":["LEG_11237","LEG_1798","LEG_754"],"CIOR_JPIH":["LEG_11237","LEG_1794","LEG_202"],"CIOR_DBCS":["LEG_11237","LEG_1798","LEG_755"],"CIOR_DPMS":["LEG_11237","LEG_1794","LEG_203"],"CIOR_DAMG":["LEG_11237","LEG_1798","LEG_756"],"CIOR_DCFA":["LEG_11237","LEG_1804","LEG_525"],"CIOR_ECOA":["LEG_11237","LEG_1796","LEG_526"],"CIOR_EAAS":["LEG_11237","LEG_1797","LEG_759"],"CIOR_EMBC":["LEG_11237","LEG_1798","LEG_760"],"CIOR_EIOM":["LEG_11237","LEG_1794","LEG_207"],"CIOR_CCXH":["LEG_75904","LEG_1794","LEG_78303"],"CIOR_EKCC":["LEG_11237","LEG_1804","LEG_528"],"CIOR_ECFA":["LEG_11237","LEG_1804","LEG_529"],"CIOR_ETCI":["LEG_11237","LEG_1793","LEG_211"],"CIOR_FACD":["LEG_11237","LEG_1804","LEG_530"],"CIOR_FBCC":["LEG_11237","LEG_1804","LEG_531"],"CIOR_FCK":["LEG_75904","LEG_83698","LEG_83666"],"CIOR_FIOM":["LEG_75904","LEG_83698","LEG_83668"],"CIOR_FTCF":["LEG_75904","LEG_83698","LEG_83670"],"CIOR_FAAS":["LEG_11250"],"CIOR_GAAS":["LEG_11237","LEG_1804","LEG_535"],"CIOR_GHAA":["LEG_11237","LEG_1798","LEG_770"],"CIOR_GCKK":["LEG_11237","LEG_1798","LEG_771"],"CIOR_GASC":["LEG_11251"],"CIOR_GCM":["LEG_11237","LEG_1804","LEG_538"],"CIOR_RCTY":["LEG_11237","LEG_1804","LEG_539"],"CIOR_EVZE":["LEG_11237","LEG_1796","LEG_540"],"CIOR_CBRK":["LEG_75904","LEG_1798","LEG_77947"],"CIOR_KAIN":["LEG_11252"],"CIOR_XOGR":["LEG_11237","LEG_1797","LEG_778"],"CIOR_WUTE":["LEG_11237","LEG_1797","LEG_779"],"CIOR_IODZ":["LEG_11237","LEG_1797","LEG_780"],"CIOR_BMSE":["LEG_75904","LEG_1794","LEG_77639"],"CIOR_PCSZ":["LEG_11237","LEG_1809","LEG_228"],"CIOR_ALOU":["LEG_75904","LEG_1809","LEG_77019"],"CIOR_GCOP":["LEG_11237","LEG_1798","LEG_781"],"CIOR_GCOT":["LEG_11237","LEG_1798","LEG_782"],"CIOR_YNGR":["LEG_11237","LEG_1804","LEG_544"],"CIOR_GVCO":["LEG_11237","LEG_1804","LEG_545"],"CIOR_GCOA":["LEG_11237","LEG_1798","LEG_785"],"CIOR_HGMW":["LEG_11237","LEG_1804","LEG_547"],"CIOR_HAAS":["LEG_11237","LEG_1797","LEG_787"],"CIOR_HCOA":["LEG_11253"],"CIOR_HMCO":["LEG_11237","LEG_1804","LEG_548"],"CIOR_HPKC":["LEG_11237","LEG_1794","LEG_237"],"CIOR_HCIO":["LEG_11237","LEG_1798","LEG_790"],"CIOR_HGAO":["LEG_11237","LEG_1794","LEG_239"],"CIOR_XUJC":["LEG_11237","LEG_1794","LEG_240"],"CIOR_IAAS":["LEG_11254"],"CIOR_ICFA":["LEG_11237","LEG_1809","LEG_242"],"CIOR_ICOA":["LEG_11237","LEG_1797","LEG_792"],"CIOR_ITCP":["LEG_11255"],"CIOR_JTTG":["LEG_11237","LEG_1794","LEG_245"],"CIOR_IMAA":["LEG_11237","LEG_1804","LEG_550"],"CIOR_IASC":["LEG_11237","LEG_1798","LEG_795"],"CIOR_LKLX":["LEG_11256"],"CIOR_IOAS":["LEG_11237","LEG_1794","LEG_249"],"CIOR_IIAC":["LEG_11237","LEG_1796","LEG_552"],"CIOR_XHDK":["LEG_11257"],"CIOR_ICOT":["LEG_11258"],"CIOR_ICSB":["LEG_11237","LEG_1798","LEG_800"],"CIOR_JWAC":["LEG_11237","LEG_1798","LEG_801"],"CIOR_JNAS":["LEG_11237","LEG_1804","LEG_555"],"CIOR_JNTC":["LEG_11237","LEG_1804","LEG_556"],"CIOR_JNWA":["LEG_11237","LEG_1804","LEG_557"],"CIOR_JIAA":["LEG_11237","LEG_1804","LEG_558"],"CIOR_JAAS":["LEG_11237","LEG_1798","LEG_806"],"CIOR_JICO":["LEG_11237","LEG_1798","LEG_807"],"CIOR_JTCM":["LEG_11237","LEG_1794","LEG_257"],"CIOR_JCOA":["LEG_11237","LEG_1804","LEG_561"],"CIOR_JTCK":["LEG_11237","LEG_1794","LEG_259"],"CIOR_KMCO":["LEG_11237","LEG_1798","LEG_809"],"CIOR_KTMC":["LEG_11259"],"CIOR_KPX":["LEG_11237","LEG_1794","LEG_261"],"CIOR_KACT":["LEG_11237","LEG_1796","LEG_563"],"CIOR_KSCK":["LEG_11237","LEG_1798","LEG_812"],"CIOR_KUMD":["LEG_11237","LEG_1809","LEG_263"],"CIOR_KASC":["LEG_11237","LEG_1797","LEG_813"],"CIOR_KCAU":["LEG_11237","LEG_1798","LEG_814"],"CIOR_KPAT":["LEG_11237","LEG_1794","LEG_265"],"CIOR_KCOT":["LEG_11237","LEG_1798","LEG_815"],"CIOR_FHDX":["LEG_11237","LEG_1804","LEG_567"],"CIOR_KCOD":["LEG_11237","LEG_1794","LEG_267"],"CIOR_KAAS":["LEG_11237","LEG_1809","LEG_268"],"CIOR_STEJ":["LEG_11237","LEG_1798","LEG_817"],"CIOR_KCOE":["LEG_11237","LEG_1798","LEG_818"],"CIOR_TMOV":["LEG_11237","LEG_1798","LEG_819"],"CIOR_KAHM":["LEG_11237","LEG_1804","LEG_571"],"CIOR_KFAA":["LEG_11237","LEG_1804","LEG_572"],"CIOR_EERX":["LEG_11237","LEG_1804","LEG_573"],"CIOR_KSNC":["LEG_11237","LEG_1809","LEG_272"],"CIOR_VEKH":["LEG_11260"],"CIOR_QHPR":["LEG_11237","LEG_1798","LEG_824"],"CIOR_KGAS":["LEG_11237","LEG_1798","LEG_825"],"CIOR_LNAA":["LEG_11261"],"CIOR_LMDC":["LEG_11237","LEG_1796","LEG_576"],"CIOR_LCOA":["LEG_11262"],"CIOR_LFIO":["LEG_11237","LEG_1798","LEG_829"],"CIOR_LAAS":["LEG_11237","LEG_1809","LEG_280"],"CIOR_MASC":["LEG_11237","LEG_1798","LEG_830"],"CIOR_SPGF":["LEG_11237","LEG_1798","LEG_831"],"CIOR_MAAS":["LEG_11237","LEG_1809","LEG_281"],"CIOR_QFGD":["LEG_11263"],"CIOR_KNFJ":["LEG_11264"],"CIOR_MCV":["LEG_11237","LEG_1797","LEG_834"],"CIOR_MKCV":["LEG_11237","LEG_1809","LEG_286"],"CIOR_MMC":["LEG_11265"],"CIOR_MPC":["LEG_11237","LEG_1809","LEG_288"],"CIOR_MCOA":["LEG_11237","LEG_1797","LEG_836"],"CIOR_MTCP":["LEG_11237","LEG_1809","LEG_290"],"CIOR_MMSN":["LEG_11266"],"CIOR_FCKE":["LEG_11267"],"CIOR_NYDL":["LEG_11237","LEG_1809","LEG_293"],"CIOR_VASP":["LEG_11237","LEG_1804","LEG_581"],"CIOR_MGIO":["LEG_11237","LEG_1804","LEG_582"],"CIOR_MUAC":["LEG_11237","LEG_1796","LEG_583"],"CIOR_MTCM":["LEG_11268"],"CIOR_QTRL":["LEG_11237","LEG_1798","LEG_843"],"CIOR_DBJV":["LEG_11237","LEG_1809","LEG_298"],"CIOR_YCOK":["LEG_11237","LEG_1798","LEG_844"],"CIOR_MTCR":["LEG_11237","LEG_1798","LEG_845"],"CIOR_XLQJ":["LEG_11237","LEG_1797","LEG_846"],"CIOR_MCCC":["LEG_11237","LEG_1798","LEG_847"],"CIOR_YOCB":["LEG_11237","LEG_1804","LEG_588"],"CIOR_WGGT":["LEG_11237","LEG_1798","LEG_849"],"CIOR_MCOC":["LEG_11237","LEG_1804","LEG_590"],"CIOR_JFLI":["LEG_11237","LEG_1798","LEG_851"],"CIOR_MBCO":["LEG_11237","LEG_1798","LEG_852"],"CIOR_MDCP":["LEG_11237","LEG_1794","LEG_302"],"CIOR_MOCP":["LEG_11269"],"CIOR_MOTC":["LEG_11270"],"CIOR_WPEP":["LEG_11237","LEG_1809","LEG_306"],"CIOR_WDXW":["LEG_11237","LEG_1798","LEG_855"],"CIOR_MOCT":["LEG_11271"],"CIOR_MTCA":["LEG_11237","LEG_1809","LEG_308"],"CIOR_MWWC":["LEG_11237","LEG_1798","LEG_857"],"CIOR_MCC":["LEG_11272"],"CIOR_MAKA":["LEG_11237","LEG_1804","LEG_595"],"CIOR_HIKB":["LEG_11237","LEG_1804","LEG_596"],"CIOR_MSCO":["LEG_11237","LEG_1797","LEG_861"],"CIOR_MCOT":["LEG_11237","LEG_1797","LEG_862"],"CIOR_AHPE":["LEG_75904","LEG_1794","LEG_76767"],"CIOR_BECF":["LEG_75904","LEG_1797","LEG_77364"],"CIOR_MCOS":["LEG_11237","LEG_1797","LEG_864"],"CIOR_SVBW":["LEG_11237","LEG_1796","LEG_597"],"CIOR_UKSD":["LEG_11237","LEG_1809","LEG_318"],"CIOR_MCM":["LEG_11237","LEG_1798","LEG_866"],"CIOR_MIIO":["LEG_11273"],"CIOR_SSLJ":["LEG_11237","LEG_1797","LEG_868"],"CIOR_RPIU":["LEG_11237","LEG_1794","LEG_322"],"CIOR_MTCO":["LEG_11237","LEG_1797","LEG_869"],"CIOR_YVQG":["LEG_11237","LEG_1804","LEG_599"],"CIOR_LXAJ":["LEG_11237","LEG_1804","LEG_600"],"CIOR_RCNF":["LEG_11274"],"CIOR_MARM":["LEG_11237","LEG_1798","LEG_873"],"CIOR_MOCO":["LEG_11237","LEG_1798","LEG_874"],"CIOR_NGCK":["LEG_11237","LEG_1798","LEG_875"],"CIOR_NCM":["LEG_11237","LEG_1804","LEG_604"],"CIOR_NBSK":["LEG_11237","LEG_1794","LEG_328"],"CIOR_NIOM":["LEG_11237","LEG_1794","LEG_329"],"CIOR_NCOS":["LEG_11275"],"CIOR_NCOT":["LEG_11237","LEG_1794","LEG_332"],"CIOR_NCOA":["LEG_11276"],"CIOR_YBKE":["LEG_11237","LEG_1797","LEG_879"],"CIOR_NESA":["LEG_11237","LEG_1794","LEG_335"],"CIOR_OMYK":["LEG_11237","LEG_1794","LEG_336"],"CIOR_QLBF":["LEG_11237","LEG_1794","LEG_338"],"CIOR_NWCM":["LEG_11237","LEG_1804","LEG_605"],"CIOR_JNZP":["LEG_11237","LEG_1809","LEG_340"],"CIOR_NTC":["LEG_11277"],"CIOR_PYDS":["LEG_11278"],"CIOR_OCOH":["LEG_11237","LEG_1798","LEG_883"],"CIOR_OCOT":["LEG_11237","LEG_1798","LEG_884"],"CIOR_OSOH":["LEG_11237","LEG_1798","LEG_885"],"CIOR_PVSC":["LEG_11237","LEG_1798","LEG_886"],"CIOR_PMST":["LEG_11237","LEG_1796","LEG_610"],"CIOR_PPTM":["LEG_11237","LEG_1796","LEG_611"],"CIOR_PMGC":["LEG_11237","LEG_1794","LEG_345"],"CIOR_PCOA":["LEG_11237","LEG_1794","LEG_346"],"CIOR_PRCP":["LEG_11237","LEG_1798","LEG_889"],"CIOR_PCAA":["LEG_11237","LEG_1798","LEG_890"],"CIOR_PDLC":["LEG_11279"],"CIOR_PSMO":["LEG_11237","LEG_1796","LEG_614"],"CIOR_PTMG":["LEG_11280"],"CIOR_PMHT":["LEG_11237","LEG_1794","LEG_350"],"CIOR_PNCP":["LEG_11237","LEG_1794","LEG_351"],"CIOR_PAAS":["LEG_11237","LEG_1809","LEG_352"],"CIOR_PVCO":["LEG_11237","LEG_1804","LEG_615"],"CIOR_PASC":["LEG_11237","LEG_1804","LEG_616"],"CIOR_PCOT":["LEG_11237","LEG_1798","LEG_896"],"CIOR_PWCM":["LEG_11237","LEG_1798","LEG_897"],"CIOR_RMSY":["LEG_11237","LEG_1798","LEG_898"],"CIOR_RACK":["LEG_11237","LEG_1797","LEG_899"],"CIOR_RCOS":["LEG_11237","LEG_1796","LEG_620"],"CIOR_RUAC":["LEG_75904","LEG_83698","LEG_83672"],"CIOR_WHEU":["LEG_75904","LEG_83698","LEG_83674"],"CIOR_RCOA":["LEG_11237","LEG_1809","LEG_359"],"CIOR_SAAS":["LEG_11237","LEG_1797","LEG_903"],"CIOR_SYMR":["LEG_11237","LEG_1798","LEG_904"],"CIOR_SHCF":["LEG_11237","LEG_1794","LEG_361"],"CIOR_SACP":["LEG_11237","LEG_1809","LEG_363"],"CIOR_SCOA":["LEG_11237","LEG_1809","LEG_364"],"CIOR_SIOA":["LEG_11237","LEG_1798","LEG_905"],"CIOR_JCLJ":["LEG_11237","LEG_1794","LEG_365"],"CIOR_SIOM":["LEG_11237","LEG_1794","LEG_366"],"CIOR_SPZS":["LEG_11281"],"CIOR_SACK":["LEG_11282"],"CIOR_SACM":["LEG_11237","LEG_1797","LEG_908"],"CIOR_SCWK":["LEG_11283"],"CIOR_STCK":["LEG_11284"],"CIOR_SEOT":["LEG_11237","LEG_1797","LEG_911"],"CIOR_SIAC":["LEG_11237","LEG_1797","LEG_912"],"CIOR_SDSM":["LEG_11237","LEG_1798","LEG_913"],"CIOR_SMAS":["LEG_11237","LEG_1809","LEG_374"],"CIOR_SASC":["LEG_11237","LEG_1794","LEG_375"],"CIOR_SODA":["LEG_11237","LEG_1794","LEG_376"],"CIOR_MBQF":["LEG_11237","LEG_1798","LEG_914"],"CIOR_PEMA":["LEG_11237","LEG_1809","LEG_377"],"CIOR_TASU":["LEG_11237","LEG_1797","LEG_915"],"CIOR_WTSR":["LEG_11237","LEG_1794","LEG_380"],"CIOR_LGNA":["LEG_11285"],"CIOR_SCFW":["LEG_11237","LEG_1796","LEG_627"],"CIOR_QFIP":["LEG_11237","LEG_1797","LEG_918"],"CIOR_SHAS":["LEG_11237","LEG_1797","LEG_919"],"CIOR_SHIO":["LEG_11237","LEG_1797","LEG_920"],"CIOR_SYSS":["LEG_11286"],"CIOR_AEUZ":["LEG_75904","LEG_1798","LEG_76665"],"CIOR_WIUZ":["LEG_11237","LEG_1798","LEG_923"],"CIOR_SGAA":["LEG_11237","LEG_1794","LEG_388"],"CIOR_MEWQ":["LEG_11237","LEG_1798","LEG_924"],"CIOR_SKCT":["LEG_11237","LEG_1794","LEG_389"],"CIOR_SKVB":["LEG_11287"],"CIOR_BFMH":["LEG_75904","LEG_1798","LEG_77452"],"CIOR_SFLH":["LEG_11288"],"CIOR_SNCV":["LEG_11237","LEG_1797","LEG_928"],"CIOR_DLGH":["LEG_11237","LEG_1798","LEG_929"],"CIOR_YANP":["LEG_11237","LEG_1794","LEG_394"],"CIOR_SNCC":["LEG_11237","LEG_1798","LEG_930"],"CIOR_SNGS":["LEG_11289"],"CIOR_SSCE":["LEG_11237","LEG_1804","LEG_634"],"CIOR_SSVC":["LEG_11290"],"CIOR_SVCO":["LEG_11291"],"CIOR_SVCK":["LEG_11237","LEG_1794","LEG_400"],"CIOR_SVPK":["LEG_11292"],"CIOR_SVTE":["LEG_11237","LEG_1794","LEG_402"],"CIOR_SVNC":["LEG_11293"],"CIOR_JDNC":["LEG_11237","LEG_1809","LEG_404"],"CIOR_SSSS":["LEG_11237","LEG_1797","LEG_937"],"CIOR_SCGC":["LEG_11237","LEG_1794","LEG_406"],"CIOR_KSQV":["LEG_11237","LEG_1798","LEG_938"],"CIOR_SACE":["LEG_11237","LEG_1794","LEG_407"],"CIOR_SJCD":["LEG_11237","LEG_1798","LEG_939"],"CIOR_SJCI":["LEG_11237","LEG_1793","LEG_408"],"CIOR_SMCP":["LEG_11294"],"CIOR_SMCS":["LEG_11237","LEG_1798","LEG_941"],"CIOR_STAA":["LEG_11237","LEG_1794","LEG_410"],"CIOR_SXAA":["LEG_11237","LEG_1798","LEG_942"],"CIOR_SBCP":["LEG_11237","LEG_1797","LEG_943"],"CIOR_SJAA":["LEG_11237","LEG_1794","LEG_412"],"CIOR_SJTC":["LEG_11237","LEG_1794","LEG_413"],"CIOR_STTC":["LEG_11237","LEG_1798","LEG_944"],"CIOR_SCT":["LEG_11237","LEG_1794","LEG_414"],"CIOR_SACA":["LEG_11237","LEG_1798","LEG_945"],"CIOR_FDJM":["LEG_11237","LEG_1798","LEG_946"],"CIOR_SSCA":["LEG_11237","LEG_1798","LEG_947"],"CIOR_SACC":["LEG_11237","LEG_1798","LEG_948"],"CIOR_TQJV":["LEG_11237","LEG_1798","LEG_949"],"CIOR_SARB":["LEG_11237","LEG_1798","LEG_950"],"CIOR_TTCN":["LEG_11237","LEG_1797","LEG_951"],"CIOR_TAAC":["LEG_11237","LEG_1809","LEG_416"],"CIOR_TAAS":["LEG_11237","LEG_1794","LEG_417"],"CIOR_TMGT":["LEG_11237","LEG_1804","LEG_646"],"CIOR_UCOA":["LEG_11237","LEG_1794","LEG_421"],"CIOR_UCFP":["LEG_11237","LEG_1798","LEG_953"],"CIOR_UTEC":["LEG_11237","LEG_1794","LEG_423"],"CIOR_QAAW":["LEG_11237","LEG_1798","LEG_954"],"CIOR_ROHW":["LEG_11237","LEG_1796","LEG_649"],"CIOR_BNSK":["LEG_75904","LEG_1794","LEG_77689"],"CIOR_EFYF":["LEG_11237","LEG_1804","LEG_650"],"CIOR_VPRO":["LEG_11237","LEG_1798","LEG_957"],"CIOR_GBEQ":["LEG_11237","LEG_1797","LEG_958"],"CIOR_NWSW":["LEG_11237","LEG_1794","LEG_429"],"CIOR_GOPO":["LEG_11237","LEG_1798","LEG_959"],"CIOR_VKHM":["LEG_11237","LEG_1798","LEG_960"],"CIOR_VPEC":["LEG_11295"],"CIOR_VCOA":["LEG_11237","LEG_1798","LEG_962"],"CIOR_VCT":["LEG_11237","LEG_1794","LEG_432"],"CIOR_WSCM":["LEG_11237","LEG_1798","LEG_963"],"CIOR_WAAS":["LEG_11296"],"CIOR_ZGCC":["LEG_11237","LEG_1798","LEG_965"]}