{"DAMC_UOC":["LEG_1394"],"DAMC_AACT":["LEG_2802"],"DAMC_AIWA":["LEG_4294"],"DAMC_BASC":["LEG_6280"],"DAMC_VPGG":["LEG_10288"],"DAMC_TXFN":["LEG_12143"],"DAMC_ECOA":["LEG_12145"],"DAMC_EVZE":["LEG_12147"],"DAMC_IIAC":["LEG_12149"],"DAMC_KACT":["LEG_12151"],"DAMC_LMDC":["LEG_12153"],"DAMC_MUAC":["LEG_12155"],"DAMC_SVBW":["LEG_12157"],"DAMC_PMST":["LEG_12159"],"DAMC_PPTM":["LEG_12161"],"DAMC_PSMO":["LEG_12163"],"DAMC_RCOS":["LEG_12165"],"DAMC_SCFW":["LEG_12167"],"DAMC_ROHW":["LEG_12169"],"DAMC_ALA":["LEG_28144","LEG_28000","LEG_27980"],"DAMC_ASM":["LEG_28144","LEG_28744","LEG_52"],"DAMC_CTR":["LEG_28144","LEG_28000","LEG_28943"],"DAMC_LFC":["LEG_28144","LEG_29069","LEG_29061"],"DAMC_MCY":["LEG_28144","LEG_28000","LEG_29186"],"DAMC_MKD":["LEG_28144","LEG_28000","LEG_29302"],"DAMC_NAT":["LEG_28144","LEG_28744","LEG_57"],"DAMC_NEM":["LEG_28144","LEG_28000","LEG_29533"],"DAMC_OTP":["LEG_28144","LEG_29669","LEG_29653"],"DAMC_PRK":["LEG_28144","LEG_28000","LEG_30061"],"DAMC_SNGS":["LEG_28144","LEG_29669","LEG_30179"],"DAMC_SKG":["LEG_28144","LEG_29069","LEG_30465"],"DAMC_SMT":["LEG_28144","LEG_29069","LEG_30581"],"DAMC_VIC":["LEG_28144","LEG_28000","LEG_31183"],"DAMC_AHMI":["LEG_28144","LEG_29069","LEG_27977"],"DAMC_AHAA":["LEG_28144","LEG_30698","LEG_27982"],"DAMC_ACOA":["LEG_28144","LEG_28000","LEG_28729"],"DAMC_AAAS":["LEG_31789"],"DAMC_ASOC":["LEG_28144","LEG_28000","LEG_28733"],"DAMC_ASOM":["LEG_28144","LEG_28000","LEG_28735"],"DAMC_AIAA":["LEG_32221"],"DAMC_AJAA":["LEG_28144","LEG_29669","LEG_30704"],"DAMC_ASCO":["LEG_28144","LEG_29669","LEG_30706"],"DAMC_AOAC":["LEG_28144","LEG_28000","LEG_28741"],"DAMC_AACN":["LEG_28144","LEG_30698","LEG_27995"],"DAMC_QZSP":["LEG_33667"],"DAMC_ACT":["LEG_33867"],"DAMC_FITC":["LEG_28144","LEG_29669","LEG_30712"],"DAMC_WCEK":["LEG_28144","LEG_29669","LEG_30714"],"DAMC_AAMC":["LEG_28144","LEG_29669","LEG_30716"],"DAMC_AACV":["LEG_34925"],"DAMC_ATCF":["LEG_28144","LEG_29669","LEG_30720"],"DAMC_AWCP":["LEG_28144","LEG_29669","LEG_30722"],"DAMC_AIAC":["LEG_35755"],"DAMC_XRLI":["LEG_35953"],"DAMC_AIAT":["LEG_28144","LEG_29669","LEG_30728"],"DAMC_AIFT":["LEG_28144","LEG_29669","LEG_30730"],"DAMC_NMLY":["LEG_37045"],"DAMC_AACP":["LEG_37259"],"DAMC_FWXK":["LEG_37473"],"DAMC_ACOE":["LEG_37697"],"DAMC_ACOS":["LEG_37883"],"DAMC_ASCK":["LEG_38107"],"DAMC_BCC":["LEG_28144","LEG_30698","LEG_28043"],"DAMC_BYAA":["LEG_38523"],"DAMC_BIAC":["LEG_38795"],"DAMC_BIAS":["LEG_38987"],"DAMC_BIOM":["LEG_28144","LEG_29069","LEG_28051"],"DAMC_BCOA":["LEG_28144","LEG_28000","LEG_28763"],"DAMC_BVNA":["LEG_28144","LEG_28000","LEG_28765"],"DAMC_BVNC":["LEG_28144","LEG_28000","LEG_28767"],"DAMC_BRIO":["LEG_39563"],"DAMC_BBTC":["LEG_28144","LEG_28000","LEG_28769"],"DAMC_BUAC":["LEG_28144","LEG_29069","LEG_28057"],"DAMC_CKRM":["LEG_40279"],"DAMC_CMGC":["LEG_28144","LEG_30698","LEG_28061"],"DAMC_CCOA":["LEG_40663"],"DAMC_CURC":["LEG_28144","LEG_30698","LEG_28065"],"DAMC_CCM":["LEG_28144","LEG_29069","LEG_28067"],"DAMC_CFCS":["LEG_28144","LEG_28000","LEG_28771"],"DAMC_MDWG":["LEG_28144","LEG_29069","LEG_28069"],"DAMC_BKCS":["LEG_41331"],"DAMC_MPFT":["LEG_28144","LEG_28000","LEG_28773"],"DAMC_FNTR":["LEG_28144","LEG_29069","LEG_28073"],"DAMC_TEGU":["LEG_28144","LEG_29069","LEG_28075"],"DAMC_FIAQ":["LEG_28144","LEG_29069","LEG_28077"],"DAMC_UFHJ":["LEG_28144","LEG_29069","LEG_28079"],"DAMC_MCBJ":["LEG_42009"],"DAMC_PSUL":["LEG_28144","LEG_30698","LEG_28083"],"DAMC_AQYX":["LEG_42461"],"DAMC_ABCD":["LEG_28144","LEG_29069","LEG_28087"],"DAMC_CMKM":["LEG_42781"],"DAMC_CIOR":["LEG_28144","LEG_28000","LEG_28775"],"DAMC_CMGM":["LEG_28144","LEG_28000","LEG_28777"],"DAMC_CCOS":["LEG_28144","LEG_29669","LEG_30764"],"DAMC_CCOM":["LEG_28144","LEG_29069","LEG_28093"],"DAMC_CGAA":["LEG_43559"],"DAMC_CCI":["LEG_28144","LEG_28744","LEG_28098"],"DAMC_CCOT":["LEG_43834"],"DAMC_CAAS":["LEG_28144","LEG_30698","LEG_28103"],"DAMC_COAS":["LEG_28144","LEG_29669","LEG_30770"],"DAMC_MWZB":["LEG_28144","LEG_28000","LEG_28783"],"DAMC_XGNZ":["LEG_28144","LEG_28000","LEG_28785"],"DAMC_PLCT":["LEG_28144","LEG_30698","LEG_28107"],"DAMC_JWRH":["LEG_44798"],"DAMC_VVFQ":["LEG_28144","LEG_29069","LEG_28111"],"DAMC_FKIA":["LEG_45066"],"DAMC_ZPEB":["LEG_28144","LEG_28000","LEG_28787"],"DAMC_YHST":["LEG_28144","LEG_28000","LEG_28789"],"DAMC_MHFR":["LEG_28144","LEG_29069","LEG_28117"],"DAMC_PELD":["LEG_45830"],"DAMC_NOBD":["LEG_28144","LEG_28000","LEG_28791"],"DAMC_RLPO":["LEG_46094"],"DAMC_FIEY":["LEG_46296"],"DAMC_CRCF":["LEG_46470"],"DAMC_CCOG":["LEG_46648"],"DAMC_CCMW":["LEG_28144","LEG_30698","LEG_28129"],"DAMC_DMAC":["LEG_47076"],"DAMC_SXMT":["LEG_47246"],"DAMC_DUAC":["LEG_47416"],"DAMC_DUTC":["LEG_47586"],"DAMC_DAAS":["LEG_47756"],"DAMC_DPIO":["LEG_47924"],"DAMC_DCOA":["LEG_28144","LEG_28000","LEG_28793"],"DAMC_KWHT":["LEG_28144","LEG_30698","LEG_28147"],"DAMC_DIOM":["LEG_28144","LEG_29069","LEG_28149"],"DAMC_DBCM":["LEG_48171"],"DAMC_JPIH":["LEG_28144","LEG_29069","LEG_28153"],"DAMC_DBCS":["LEG_48173"],"DAMC_DPMS":["LEG_28144","LEG_29069","LEG_28157"],"DAMC_DAMG":["LEG_48175"],"DAMC_DCFA":["LEG_48177"],"DAMC_EAAS":["LEG_28144","LEG_30698","LEG_28165"],"DAMC_EMBC":["LEG_48179"],"DAMC_EIOM":["LEG_28144","LEG_29069","LEG_28169"],"DAMC_CCXH":["LEG_28144","LEG_29069","LEG_28171"],"DAMC_EKCC":["LEG_48181"],"DAMC_ECFA":["LEG_48183"],"DAMC_ETCI":["LEG_28144","LEG_28744","LEG_28177"],"DAMC_ETCM":["LEG_28144","LEG_28000","LEG_28795"],"DAMC_FACD":["LEG_48185"],"DAMC_FBCC":["LEG_48187"],"DAMC_FCK":["LEG_48189"],"DAMC_FIOM":["LEG_48191"],"DAMC_FTCF":["LEG_48193"],"DAMC_FAAS":["LEG_28144","LEG_29669","LEG_30822"],"DAMC_GAAS":["LEG_48195"],"DAMC_GHAA":["LEG_48197"],"DAMC_GCKK":["LEG_48199"],"DAMC_GASC":["LEG_28144","LEG_29669","LEG_30830"],"DAMC_GCM":["LEG_48201"],"DAMC_RCTY":["LEG_48203"],"DAMC_CBRK":["LEG_48205"],"DAMC_KAIN":["LEG_28144","LEG_29669","LEG_30838"],"DAMC_EKUE":["LEG_28144","LEG_28000","LEG_28803"],"DAMC_XOGR":["LEG_28144","LEG_30698","LEG_28209"],"DAMC_WUTE":["LEG_28144","LEG_30698","LEG_28211"],"DAMC_IODZ":["LEG_28144","LEG_30698","LEG_28213"],"DAMC_BMSE":["LEG_28144","LEG_29069","LEG_28215"],"DAMC_YRMA":["LEG_28144","LEG_28000","LEG_28805"],"DAMC_PCSZ":["LEG_48207"],"DAMC_ALOU":["LEG_48209"],"DAMC_GCOP":["LEG_48211"],"DAMC_GCOT":["LEG_48213"],"DAMC_YNGR":["LEG_48215"],"DAMC_LYRX":["LEG_28144","LEG_28000","LEG_28807"],"DAMC_GVCO":["LEG_48217"],"DAMC_GCOA":["LEG_48219"],"DAMC_HGMW":["LEG_48221"],"DAMC_HAAS":["LEG_28144","LEG_30698","LEG_28233"],"DAMC_HCOA":["LEG_28144","LEG_29669","LEG_30856"],"DAMC_HMCO":["LEG_48223"],"DAMC_HPKC":["LEG_28144","LEG_29069","LEG_28239"],"DAMC_HCIO":["LEG_48225"],"DAMC_HFCO":["LEG_28144","LEG_28000","LEG_28811"],"DAMC_HGAO":["LEG_28144","LEG_29069","LEG_28243"],"DAMC_XUJC":["LEG_28144","LEG_29069","LEG_28245"],"DAMC_IAAS":["LEG_28144","LEG_29669","LEG_30862"],"DAMC_ICFA":["LEG_48227"],"DAMC_ICOA":["LEG_28144","LEG_30698","LEG_28251"],"DAMC_ITCP":["LEG_28144","LEG_29669","LEG_30866"],"DAMC_JTTG":["LEG_28144","LEG_29069","LEG_28255"],"DAMC_IMAA":["LEG_48229"],"DAMC_IASC":["LEG_48231"],"DAMC_LKLX":["LEG_28144","LEG_29669","LEG_30872"],"DAMC_IMTT":["LEG_28144","LEG_28000","LEG_28819"],"DAMC_IOAS":["LEG_28144","LEG_29069","LEG_28263"],"DAMC_XHDK":["LEG_28144","LEG_29669","LEG_30874"],"DAMC_ICOT":["LEG_28144","LEG_29669","LEG_30876"],"DAMC_ICSB":["LEG_48233"],"DAMC_JWAC":["LEG_48235"],"DAMC_JNAS":["LEG_48237"],"DAMC_JNTC":["LEG_48239"],"DAMC_JNWA":["LEG_48241"],"DAMC_JIAA":["LEG_48243"],"DAMC_JAAS":["LEG_48245"],"DAMC_JICO":["LEG_48247"],"DAMC_JTCM":["LEG_28144","LEG_29069","LEG_28287"],"DAMC_JCOA":["LEG_48249"],"DAMC_JTCK":["LEG_28144","LEG_29069","LEG_28291"],"DAMC_KMCO":["LEG_48251"],"DAMC_KTMC":["LEG_28144","LEG_29669","LEG_30898"],"DAMC_KPX":["LEG_28144","LEG_29069","LEG_28297"],"DAMC_KSCK":["LEG_48253"],"DAMC_KUMD":["LEG_48255"],"DAMC_KASC":["LEG_28144","LEG_30698","LEG_28305"],"DAMC_KCAU":["LEG_48257"],"DAMC_KPAT":["LEG_28144","LEG_29069","LEG_28309"],"DAMC_KCOT":["LEG_48259"],"DAMC_FHDX":["LEG_48261"],"DAMC_KCOD":["LEG_28144","LEG_29069","LEG_28315"],"DAMC_KAAS":["LEG_48263"],"DAMC_STEJ":["LEG_48265"],"DAMC_KCOE":["LEG_48267"],"DAMC_TMOV":["LEG_48269"],"DAMC_KAHM":["LEG_48271"],"DAMC_KFAA":["LEG_48273"],"DAMC_EERX":["LEG_48275"],"DAMC_KSNC":["LEG_48277"],"DAMC_VEKH":["LEG_28144","LEG_29669","LEG_30926"],"DAMC_QHPR":["LEG_48279"],"DAMC_KGAS":["LEG_48281"],"DAMC_LNAA":["LEG_28144","LEG_29669","LEG_30932"],"DAMC_LCOA":["LEG_28144","LEG_29669","LEG_30934"],"DAMC_LCOM":["LEG_28144","LEG_28000","LEG_28833"],"DAMC_LETC":["LEG_28144","LEG_28000","LEG_28835"],"DAMC_LFIO":["LEG_48283"],"DAMC_LAAS":["LEG_48285"],"DAMC_MASC":["LEG_48287"],"DAMC_SPGF":["LEG_48289"],"DAMC_MAAS":["LEG_48291"],"DAMC_QFGD":["LEG_28144","LEG_29669","LEG_30946"],"DAMC_KNFJ":["LEG_28144","LEG_29669","LEG_30948"],"DAMC_MCV":["LEG_28144","LEG_30698","LEG_28359"],"DAMC_MKSH":["LEG_28144","LEG_28000","LEG_28841"],"DAMC_MKCV":["LEG_48293"],"DAMC_MMC":["LEG_28144","LEG_29669","LEG_30952"],"DAMC_MPC":["LEG_48295"],"DAMC_MCOA":["LEG_28144","LEG_30698","LEG_28367"],"DAMC_MTCP":["LEG_48297"],"DAMC_MMSN":["LEG_28144","LEG_29669","LEG_30958"],"DAMC_FCKE":["LEG_28144","LEG_29669","LEG_30960"],"DAMC_NYDL":["LEG_48299"],"DAMC_VASP":["LEG_48301"],"DAMC_MGIO":["LEG_48303"],"DAMC_MTCM":["LEG_28144","LEG_29669","LEG_30968"],"DAMC_QTRL":["LEG_48305"],"DAMC_DBJV":["LEG_48307"],"DAMC_YCOK":["LEG_48309"],"DAMC_MTCR":["LEG_48311"],"DAMC_XLQJ":["LEG_28144","LEG_30698","LEG_28393"],"DAMC_MCCC":["LEG_48313"],"DAMC_YOCB":["LEG_48315"],"DAMC_WGGT":["LEG_48317"],"DAMC_MCOC":["LEG_48319"],"DAMC_JFLI":["LEG_48321"],"DAMC_MBCO":["LEG_48323"],"DAMC_MDCP":["LEG_28144","LEG_29069","LEG_28407"],"DAMC_MOCP":["LEG_28144","LEG_29669","LEG_30990"],"DAMC_MOTC":["LEG_28144","LEG_29669","LEG_30992"],"DAMC_GIWF":["LEG_28144","LEG_28000","LEG_28855"],"DAMC_WPEP":["LEG_48325"],"DAMC_WDXW":["LEG_48327"],"DAMC_MOCT":["LEG_28144","LEG_29669","LEG_30998"],"DAMC_MTCA":["LEG_48329"],"DAMC_MWWC":["LEG_48331"],"DAMC_MCC":["LEG_28144","LEG_29669","LEG_31004"],"DAMC_MAKA":["LEG_48333"],"DAMC_HIKB":["LEG_48335"],"DAMC_MSCO":["LEG_28144","LEG_30698","LEG_28429"],"DAMC_MCOT":["LEG_28144","LEG_30698","LEG_28431"],"DAMC_AHPE":["LEG_28144","LEG_29069","LEG_28433"],"DAMC_BECF":["LEG_28144","LEG_30698","LEG_28435"],"DAMC_MCOS":["LEG_28144","LEG_30698","LEG_28437"],"DAMC_UKSD":["LEG_48337"],"DAMC_MCM":["LEG_48339"],"DAMC_MIIO":["LEG_28144","LEG_29669","LEG_31014"],"DAMC_MICP":["LEG_28144","LEG_28000","LEG_28863"],"DAMC_SSLJ":["LEG_28144","LEG_30698","LEG_28447"],"DAMC_RPIU":["LEG_28144","LEG_29069","LEG_28449"],"DAMC_MTCO":["LEG_28144","LEG_30698","LEG_28451"],"DAMC_YVQG":["LEG_48341"],"DAMC_LXAJ":["LEG_48343"],"DAMC_RCNF":["LEG_28144","LEG_29669","LEG_31020"],"DAMC_MARM":["LEG_48345"],"DAMC_MOCO":["LEG_48347"],"DAMC_NGCK":["LEG_48349"],"DAMC_NCM":["LEG_48351"],"DAMC_NBSK":["LEG_28144","LEG_29069","LEG_28467"],"DAMC_NIOM":["LEG_28144","LEG_29069","LEG_28469"],"DAMC_NAAS":["LEG_28144","LEG_28000","LEG_28867"],"DAMC_NCOS":["LEG_28144","LEG_29669","LEG_31030"],"DAMC_NCOT":["LEG_28144","LEG_29069","LEG_28473"],"DAMC_NCOA":["LEG_28144","LEG_29669","LEG_31032"],"DAMC_YBKE":["LEG_28144","LEG_30698","LEG_28477"],"DAMC_NESA":["LEG_28144","LEG_29069","LEG_28479"],"DAMC_OMYK":["LEG_28144","LEG_29069","LEG_28481"],"DAMC_NMAA":["LEG_28144","LEG_28000","LEG_28873"],"DAMC_QLBF":["LEG_28144","LEG_29069","LEG_28483"],"DAMC_NWCM":["LEG_48353"],"DAMC_JNZP":["LEG_48355"],"DAMC_NTC":["LEG_28144","LEG_29669","LEG_31038"],"DAMC_PYDS":["LEG_28144","LEG_29669","LEG_31040"],"DAMC_OCOH":["LEG_48357"],"DAMC_OCOT":["LEG_48359"],"DAMC_OSOH":["LEG_48361"],"DAMC_PVSC":["LEG_48363"],"DAMC_PMGC":["LEG_28144","LEG_29069","LEG_28505"],"DAMC_PCOA":["LEG_28144","LEG_29069","LEG_28507"],"DAMC_PRCP":["LEG_48365"],"DAMC_PCAA":["LEG_48367"],"DAMC_PDLC":["LEG_28144","LEG_29669","LEG_31054"],"DAMC_PTMG":["LEG_28144","LEG_29669","LEG_31056"],"DAMC_PMHT":["LEG_28144","LEG_29069","LEG_28519"],"DAMC_PNCP":["LEG_28144","LEG_29069","LEG_28521"],"DAMC_PAAS":["LEG_48369"],"DAMC_PFFE":["LEG_28144","LEG_28000","LEG_28883"],"DAMC_PVCO":["LEG_48371"],"DAMC_PASC":["LEG_48373"],"DAMC_PCOT":["LEG_48375"],"DAMC_PWCM":["LEG_48377"],"DAMC_RMSY":["LEG_48379"],"DAMC_RACK":["LEG_28144","LEG_30698","LEG_28535"],"DAMC_RGMG":["LEG_28144","LEG_28000","LEG_28885"],"DAMC_RUAC":["LEG_48381"],"DAMC_WHEU":["LEG_48383"],"DAMC_RCOA":["LEG_48385"],"DAMC_SAAS":["LEG_28144","LEG_30698","LEG_28545"],"DAMC_SYMR":["LEG_48387"],"DAMC_SHCF":["LEG_28144","LEG_29069","LEG_28549"],"DAMC_SKCM":["LEG_28144","LEG_28000","LEG_28887"],"DAMC_SACP":["LEG_48389"],"DAMC_SCOA":["LEG_48391"],"DAMC_SIOA":["LEG_48393"],"DAMC_JCLJ":["LEG_28144","LEG_29069","LEG_28557"],"DAMC_SIOM":["LEG_28144","LEG_29069","LEG_28559"],"DAMC_SPZS":["LEG_28144","LEG_29669","LEG_31084"],"DAMC_SACK":["LEG_28144","LEG_29669","LEG_31086"],"DAMC_SACM":["LEG_28144","LEG_30698","LEG_28565"],"DAMC_SCWK":["LEG_28144","LEG_29669","LEG_31088"],"DAMC_STCK":["LEG_28144","LEG_29669","LEG_31090"],"DAMC_SEOT":["LEG_28144","LEG_30698","LEG_28571"],"DAMC_SIAC":["LEG_28144","LEG_30698","LEG_28573"],"DAMC_SDSM":["LEG_48395"],"DAMC_SMAS":["LEG_48397"],"DAMC_SASC":["LEG_28144","LEG_29069","LEG_28579"],"DAMC_SODA":["LEG_28144","LEG_29069","LEG_28581"],"DAMC_MBQF":["LEG_48399"],"DAMC_PEMA":["LEG_48401"],"DAMC_MVKH":["LEG_28144","LEG_28000","LEG_28897"],"DAMC_TASU":["LEG_28144","LEG_30698","LEG_28587"],"DAMC_WTSR":["LEG_28144","LEG_29069","LEG_28589"],"DAMC_LGNA":["LEG_28144","LEG_29669","LEG_31100"],"DAMC_QFIP":["LEG_28144","LEG_30698","LEG_28595"],"DAMC_SHAS":["LEG_28144","LEG_30698","LEG_28597"],"DAMC_SHIO":["LEG_28144","LEG_30698","LEG_28599"],"DAMC_SYSS":["LEG_28144","LEG_29669","LEG_31102"],"DAMC_SCOT":["LEG_28144","LEG_28000","LEG_28903"],"DAMC_AEUZ":["LEG_48403"],"DAMC_WIUZ":["LEG_48405"],"DAMC_SGAA":["LEG_28144","LEG_29069","LEG_28607"],"DAMC_MEWQ":["LEG_48407"],"DAMC_SKCT":["LEG_28144","LEG_29069","LEG_28611"],"DAMC_SKVB":["LEG_28144","LEG_29669","LEG_31110"],"DAMC_SNCO":["LEG_28144","LEG_28000","LEG_28907"],"DAMC_BFMH":["LEG_48409"],"DAMC_SFLH":["LEG_28144","LEG_29669","LEG_31114"],"DAMC_SNCV":["LEG_28144","LEG_30698","LEG_28619"],"DAMC_DLGH":["LEG_48411"],"DAMC_YANP":["LEG_28144","LEG_29069","LEG_28623"],"DAMC_SNCC":["LEG_48413"],"DAMC_SRVG":["LEG_28144","LEG_28000","LEG_28911"],"DAMC_SSCE":["LEG_48415"],"DAMC_SSVC":["LEG_28144","LEG_29669","LEG_31122"],"DAMC_SVCO":["LEG_28144","LEG_29669","LEG_31124"],"DAMC_SVCK":["LEG_28144","LEG_29069","LEG_28633"],"DAMC_SVPK":["LEG_28144","LEG_29669","LEG_31126"],"DAMC_SVTE":["LEG_28144","LEG_29069","LEG_28637"],"DAMC_SVNC":["LEG_28144","LEG_29669","LEG_31128"],"DAMC_JDNC":["LEG_48417"],"DAMC_SSSS":["LEG_28144","LEG_30698","LEG_28643"],"DAMC_SCGC":["LEG_28144","LEG_29069","LEG_28645"],"DAMC_KSQV":["LEG_48419"],"DAMC_SACE":["LEG_28144","LEG_29069","LEG_28649"],"DAMC_SJCD":["LEG_48421"],"DAMC_SJCI":["LEG_28144","LEG_28744","LEG_28651"],"DAMC_SMCP":["LEG_28144","LEG_29669","LEG_31136"],"DAMC_SMCS":["LEG_48423"],"DAMC_STAA":["LEG_28144","LEG_29069","LEG_28657"],"DAMC_SXAA":["LEG_48425"],"DAMC_SBCP":["LEG_28144","LEG_30698","LEG_28661"],"DAMC_SJAA":["LEG_28144","LEG_29069","LEG_28663"],"DAMC_SJTC":["LEG_28144","LEG_29069","LEG_28665"],"DAMC_STTC":["LEG_48427"],"DAMC_SCT":["LEG_28144","LEG_29069","LEG_28669"],"DAMC_SACA":["LEG_48429"],"DAMC_FDJM":["LEG_48431"],"DAMC_SSCA":["LEG_48433"],"DAMC_SACC":["LEG_48435"],"DAMC_TQJV":["LEG_48437"],"DAMC_SARB":["LEG_48439"],"DAMC_TTCN":["LEG_28144","LEG_30698","LEG_28683"],"DAMC_TAAC":["LEG_48441"],"DAMC_TAAS":["LEG_28144","LEG_29069","LEG_28687"],"DAMC_TECO":["LEG_28144","LEG_28000","LEG_28926"],"DAMC_TMGT":["LEG_48443"],"DAMC_TECE":["LEG_28144","LEG_28000","LEG_28928"],"DAMC_UCOA":["LEG_28144","LEG_29069","LEG_28691"],"DAMC_QNNI":["LEG_28144","LEG_28000","LEG_28930"],"DAMC_UCFP":["LEG_48445"],"DAMC_UTEC":["LEG_28144","LEG_29069","LEG_28695"],"DAMC_QAAW":["LEG_48447"],"DAMC_BNSK":["LEG_28144","LEG_29069","LEG_28701"],"DAMC_AIEB":["LEG_28144","LEG_28000","LEG_28932"],"DAMC_EFYF":["LEG_48449"],"DAMC_VPRO":["LEG_48451"],"DAMC_GBEQ":["LEG_28144","LEG_30698","LEG_28707"],"DAMC_NWSW":["LEG_28144","LEG_29069","LEG_28709"],"DAMC_GOPO":["LEG_48453"],"DAMC_VKHM":["LEG_48455"],"DAMC_VPEC":["LEG_28144","LEG_29669","LEG_31172"],"DAMC_VVCO":["LEG_28144","LEG_28000","LEG_28936"],"DAMC_VCOA":["LEG_48457"],"DAMC_VCT":["LEG_28144","LEG_29069","LEG_28719"],"DAMC_WSCM":["LEG_48459"],"DAMC_WAAS":["LEG_28144","LEG_29669","LEG_31178"],"DAMC_YIOM":["LEG_28144","LEG_28000","LEG_28940"],"DAMC_ZGCC":["LEG_48461"]}