{"MIIO_AJAA":["LEG_76927"],"MIIO_ASCO":["LEG_77162"],"MIIO_FITC":["LEG_79521"],"MIIO_WCEK":["LEG_39637"],"MIIO_AAMC":["LEG_39638"],"MIIO_ATCF":["LEG_39639"],"MIIO_AWCP":["LEG_39640"],"MIIO_AIAT":["LEG_39641"],"MIIO_AIFT":["LEG_39642"],"MIIO_CCOS":["LEG_78181"],"MIIO_COAS":["LEG_39644"],"MIIO_FAAS":["LEG_79211"],"MIIO_GASC":["LEG_39646"],"MIIO_KAIN":["LEG_39647"],"MIIO_HCOA":["LEG_39648"],"MIIO_IAAS":["LEG_39649"],"MIIO_ITCP":["LEG_39650"],"MIIO_LKLX":["LEG_39651"],"MIIO_XHDK":["LEG_39652"],"MIIO_ICOT":["LEG_80195"],"MIIO_KTMC":["LEG_81123"],"MIIO_VEKH":["LEG_39655"],"MIIO_LNAA":["LEG_81292"],"MIIO_LCOA":["LEG_81160"],"MIIO_QFGD":["LEG_39658"],"MIIO_KNFJ":["LEG_39659"],"MIIO_MMC":["LEG_39660"],"MIIO_MMSN":["LEG_39661"],"MIIO_FCKE":["LEG_79331"],"MIIO_MTCM":["LEG_39663"],"MIIO_MOCP":["LEG_39664"],"MIIO_MOTC":["LEG_39665"],"MIIO_MOCT":["LEG_39666"],"MIIO_MCC":["LEG_81464"],"MIIO_RCNF":["LEG_39668"],"MIIO_OTP":["LEG_39669"],"MIIO_NCOS":["LEG_39670"],"MIIO_NCOA":["LEG_39671"],"MIIO_NTC":["LEG_39672"],"MIIO_PYDS":["LEG_39673"],"MIIO_PDLC":["LEG_39674"],"MIIO_PTMG":["LEG_39675"],"MIIO_SPZS":["LEG_39676"],"MIIO_SACK":["LEG_39677"],"MIIO_SCWK":["LEG_39678"],"MIIO_STCK":["LEG_39679"],"MIIO_LGNA":["LEG_81251"],"MIIO_SYSS":["LEG_39681"],"MIIO_SKVB":["LEG_39682"],"MIIO_SFLH":["LEG_39683"],"MIIO_SNGS":["LEG_39684"],"MIIO_SSVC":["LEG_39685"],"MIIO_SVCO":["LEG_39686"],"MIIO_SVPK":["LEG_39687"],"MIIO_SVNC":["LEG_39688"],"MIIO_SMCP":["LEG_39689"],"MIIO_VPEC":["LEG_39690"],"MIIO_WAAS":["LEG_39691"],"MIIO_ALA":["LEG_39692"],"MIIO_ASM":["LEG_39693"],"MIIO_CTR":["LEG_39694"],"MIIO_LFC":["LEG_39695"],"MIIO_MCY":["LEG_39696"],"MIIO_MKD":["LEG_39697"],"MIIO_NAT":["LEG_39698"],"MIIO_NEM":["LEG_39699"],"MIIO_PRK":["LEG_39700"],"MIIO_SKG":["LEG_39701"],"MIIO_SMT":["LEG_39702"],"MIIO_UOC":["LEG_39703","LEG_1456","LEG_481"],"MIIO_VIC":["LEG_39704"],"MIIO_AHMI":["LEG_39705"],"MIIO_AHAA":["LEG_75987","LEG_1459","LEG_76669"],"MIIO_ACOA":["LEG_39706"],"MIIO_AAAS":["LEG_75987","LEG_1461","LEG_75857"],"MIIO_ASOC":["LEG_39707"],"MIIO_ASOM":["LEG_39708"],"MIIO_AIAA":["LEG_75987","LEG_1461","LEG_76800"],"MIIO_AOAC":["LEG_39709"],"MIIO_AACN":["LEG_75987","LEG_1459","LEG_76080"],"MIIO_AACT":["LEG_75987","LEG_1456","LEG_76334"],"MIIO_QZSP":["LEG_39703","LEG_1461","LEG_702"],"MIIO_ACT":["LEG_75987","LEG_1461","LEG_76630"],"MIIO_AACV":["LEG_75987","LEG_1465","LEG_76364"],"MIIO_AIAC":["LEG_75987","LEG_1461","LEG_76838"],"MIIO_XRLI":["LEG_39703","LEG_1461","LEG_711"],"MIIO_AIWA":["LEG_75987","LEG_1456","LEG_76896"],"MIIO_NMLY":["LEG_39710"],"MIIO_AACP":["LEG_39711"],"MIIO_FWXK":["LEG_39712"],"MIIO_ACOE":["LEG_75987","LEG_83704","LEG_83664"],"MIIO_ACOS":["LEG_39713"],"MIIO_ASCK":["LEG_75987","LEG_1461","LEG_77160"],"MIIO_BCC":["LEG_75987","LEG_1459","LEG_77321"],"MIIO_BYAA":["LEG_75987","LEG_1465","LEG_77904"],"MIIO_BIAC":["LEG_75987","LEG_1461","LEG_77480"],"MIIO_BIAS":["LEG_75987","LEG_1461","LEG_77508"],"MIIO_BIOM":["LEG_39714"],"MIIO_BCOA":["LEG_39715"],"MIIO_BVNA":["LEG_39716"],"MIIO_BVNC":["LEG_39717"],"MIIO_BRIO":["LEG_75987","LEG_1461","LEG_77788"],"MIIO_BASC":["LEG_75987","LEG_1456","LEG_77266"],"MIIO_BBTC":["LEG_39718"],"MIIO_BUAC":["LEG_39719"],"MIIO_CKRM":["LEG_75987","LEG_1461","LEG_78425"],"MIIO_CMGC":["LEG_75987","LEG_1459","LEG_78435"],"MIIO_CCOA":["LEG_75987","LEG_1461","LEG_78089"],"MIIO_CURC":["LEG_75987","LEG_1459","LEG_78564"],"MIIO_CCM":["LEG_39720"],"MIIO_CFCS":["LEG_39721"],"MIIO_MDWG":["LEG_39722"],"MIIO_BKCS":["LEG_75987","LEG_1461","LEG_77596"],"MIIO_MPFT":["LEG_39723"],"MIIO_FNTR":["LEG_39724"],"MIIO_TEGU":["LEG_39725"],"MIIO_FIAQ":["LEG_39726"],"MIIO_UFHJ":["LEG_39727"],"MIIO_MCBJ":["LEG_75987","LEG_1465","LEG_81461"],"MIIO_PSUL":["LEG_39703","LEG_1459","LEG_729"],"MIIO_AQYX":["LEG_39728"],"MIIO_ABCD":["LEG_39729"],"MIIO_CMKM":["LEG_75987","LEG_83703","LEG_83662"],"MIIO_CIOR":["LEG_39730"],"MIIO_CMGM":["LEG_39731"],"MIIO_CCOM":["LEG_39732"],"MIIO_CGAA":["LEG_75987","LEG_1461","LEG_78344"],"MIIO_CCI":["LEG_39733"],"MIIO_CCOT":["LEG_75987","LEG_1461","LEG_78253"],"MIIO_CAAS":["LEG_75987","LEG_1459","LEG_77912"],"MIIO_MWZB":["LEG_39734"],"MIIO_XGNZ":["LEG_39735"],"MIIO_PLCT":["LEG_39703","LEG_1459","LEG_736"],"MIIO_JWRH":["LEG_75987","LEG_1461","LEG_80753"],"MIIO_VVFQ":["LEG_39736"],"MIIO_FKIA":["LEG_75987","LEG_1461","LEG_79549"],"MIIO_ZPEB":["LEG_39737"],"MIIO_YHST":["LEG_39738"],"MIIO_VPGG":["LEG_39703","LEG_1456","LEG_509"],"MIIO_MHFR":["LEG_39739"],"MIIO_PELD":["LEG_39703","LEG_1461","LEG_740"],"MIIO_NOBD":["LEG_39740"],"MIIO_RLPO":["LEG_39741"],"MIIO_FIEY":["LEG_75987","LEG_1461","LEG_79471"],"MIIO_CRCF":["LEG_75987","LEG_1461","LEG_78532"],"MIIO_CCOG":["LEG_75987","LEG_1465","LEG_78130"],"MIIO_CCMW":["LEG_75987","LEG_1459","LEG_78031"],"MIIO_DMAC":["LEG_75987","LEG_1461","LEG_78874"],"MIIO_SXMT":["LEG_39703","LEG_1461","LEG_746"],"MIIO_DUAC":["LEG_75987","LEG_1461","LEG_78970"],"MIIO_DUTC":["LEG_75987","LEG_1461","LEG_79001"],"MIIO_DAAS":["LEG_75987","LEG_1461","LEG_78584"],"MIIO_DPIO":["LEG_75987","LEG_1465","LEG_78883"],"MIIO_DAMC":["LEG_75987","LEG_1456","LEG_78595"],"MIIO_DCOA":["LEG_39742"],"MIIO_TXFN":["LEG_39703","LEG_1456","LEG_521"],"MIIO_KWHT":["LEG_75987","LEG_1459","LEG_81146"],"MIIO_DIOM":["LEG_39743"],"MIIO_DBCM":["LEG_75987","LEG_1461","LEG_78646"],"MIIO_JPIH":["LEG_39744"],"MIIO_DBCS":["LEG_75987","LEG_1461","LEG_78679"],"MIIO_DPMS":["LEG_39745"],"MIIO_DAMG":["LEG_75987","LEG_1461","LEG_78618"],"MIIO_DCFA":["LEG_75987","LEG_1465","LEG_78696"],"MIIO_ECOA":["LEG_75987","LEG_1456","LEG_79027"],"MIIO_EAAS":["LEG_75987","LEG_1459","LEG_79009"],"MIIO_EMBC":["LEG_75987","LEG_1461","LEG_79139"],"MIIO_EIOM":["LEG_39746"],"MIIO_CCXH":["LEG_39747"],"MIIO_EKCC":["LEG_75987","LEG_1465","LEG_79105"],"MIIO_ECFA":["LEG_75987","LEG_1465","LEG_79019"],"MIIO_ETCI":["LEG_39748"],"MIIO_ETCM":["LEG_39749"],"MIIO_FACD":["LEG_75987","LEG_1465","LEG_79248"],"MIIO_FBCC":["LEG_75987","LEG_1465","LEG_79257"],"MIIO_FCK":["LEG_75987","LEG_83704","LEG_83666"],"MIIO_FIOM":["LEG_75987","LEG_83704","LEG_83668"],"MIIO_FTCF":["LEG_75987","LEG_83704","LEG_83670"],"MIIO_GAAS":["LEG_75987","LEG_1465","LEG_79677"],"MIIO_GHAA":["LEG_75987","LEG_1461","LEG_79865"],"MIIO_GCKK":["LEG_75987","LEG_1461","LEG_79744"],"MIIO_GCM":["LEG_75987","LEG_1465","LEG_79754"],"MIIO_RCTY":["LEG_39703","LEG_1465","LEG_539"],"MIIO_EVZE":["LEG_75987","LEG_1456","LEG_79209"],"MIIO_CBRK":["LEG_75987","LEG_1461","LEG_77947"],"MIIO_EKUE":["LEG_39750"],"MIIO_XOGR":["LEG_39703","LEG_1459","LEG_778"],"MIIO_WUTE":["LEG_39703","LEG_1459","LEG_779"],"MIIO_IODZ":["LEG_75987","LEG_1459","LEG_80319"],"MIIO_BMSE":["LEG_39751"],"MIIO_YRMA":["LEG_39752"],"MIIO_PCSZ":["LEG_39753"],"MIIO_ALOU":["LEG_39754"],"MIIO_GCOP":["LEG_75987","LEG_1461","LEG_79816"],"MIIO_GCOT":["LEG_75987","LEG_1461","LEG_79842"],"MIIO_YNGR":["LEG_39703","LEG_1465","LEG_544"],"MIIO_LYRX":["LEG_39755"],"MIIO_GVCO":["LEG_75987","LEG_1465","LEG_79909"],"MIIO_GCOA":["LEG_75987","LEG_1461","LEG_79788"],"MIIO_HGMW":["LEG_75987","LEG_1465","LEG_80075"],"MIIO_HAAS":["LEG_75987","LEG_1459","LEG_79916"],"MIIO_HMCO":["LEG_75987","LEG_1465","LEG_80088"],"MIIO_HPKC":["LEG_39756"],"MIIO_HCIO":["LEG_75987","LEG_1461","LEG_79986"],"MIIO_HFCO":["LEG_39757"],"MIIO_HGAO":["LEG_39758"],"MIIO_XUJC":["LEG_39759"],"MIIO_ICFA":["LEG_39760"],"MIIO_ICOA":["LEG_75987","LEG_1459","LEG_80193"],"MIIO_JTTG":["LEG_39761"],"MIIO_IMAA":["LEG_75987","LEG_1465","LEG_80249"],"MIIO_IASC":["LEG_75987","LEG_1461","LEG_80166"],"MIIO_IMTT":["LEG_39762"],"MIIO_IOAS":["LEG_39763"],"MIIO_IIAC":["LEG_75987","LEG_1456","LEG_80240"],"MIIO_ICSB":["LEG_75987","LEG_1461","LEG_80227"],"MIIO_JWAC":["LEG_75987","LEG_1461","LEG_80694"],"MIIO_JNAS":["LEG_75987","LEG_1465","LEG_80486"],"MIIO_JNTC":["LEG_75987","LEG_1465","LEG_80492"],"MIIO_JNWA":["LEG_75987","LEG_1465","LEG_80498"],"MIIO_JIAA":["LEG_75987","LEG_1465","LEG_80444"],"MIIO_JAAS":["LEG_75987","LEG_1461","LEG_80355"],"MIIO_JICO":["LEG_75987","LEG_1461","LEG_80480"],"MIIO_JTCM":["LEG_39764"],"MIIO_JCOA":["LEG_75987","LEG_1465","LEG_80408"],"MIIO_JTCK":["LEG_39765"],"MIIO_KMCO":["LEG_75987","LEG_1461","LEG_81011"],"MIIO_KPX":["LEG_39766"],"MIIO_KACT":["LEG_75987","LEG_1456","LEG_80782"],"MIIO_KSCK":["LEG_75987","LEG_1461","LEG_81094"],"MIIO_KUMD":["LEG_39767"],"MIIO_KASC":["LEG_75987","LEG_1459","LEG_80809"],"MIIO_KCAU":["LEG_75987","LEG_1461","LEG_80830"],"MIIO_KPAT":["LEG_39768"],"MIIO_KCOT":["LEG_75987","LEG_1461","LEG_80971"],"MIIO_FHDX":["LEG_75987","LEG_1465","LEG_79387"],"MIIO_KCOD":["LEG_39769"],"MIIO_KAAS":["LEG_39770"],"MIIO_STEJ":["LEG_39703","LEG_1461","LEG_817"],"MIIO_KCOE":["LEG_75987","LEG_1461","LEG_80917"],"MIIO_TMOV":["LEG_39703","LEG_1461","LEG_819"],"MIIO_KAHM":["LEG_75987","LEG_1465","LEG_80787"],"MIIO_KFAA":["LEG_75987","LEG_1465","LEG_80977"],"MIIO_EERX":["LEG_75987","LEG_1465","LEG_79038"],"MIIO_KSNC":["LEG_39771"],"MIIO_QHPR":["LEG_39703","LEG_1461","LEG_824"],"MIIO_KGAS":["LEG_75987","LEG_1461","LEG_80994"],"MIIO_LMDC":["LEG_75987","LEG_1456","LEG_81290"],"MIIO_LCOM":["LEG_39772"],"MIIO_LETC":["LEG_39773"],"MIIO_LFIO":["LEG_75987","LEG_1461","LEG_81237"],"MIIO_LAAS":["LEG_39774"],"MIIO_MASC":["LEG_75987","LEG_1461","LEG_81412"],"MIIO_SPGF":["LEG_39703","LEG_1461","LEG_831"],"MIIO_MAAS":["LEG_39775"],"MIIO_MCV":["LEG_75987","LEG_1459","LEG_81568"],"MIIO_MKSH":["LEG_39776"],"MIIO_MKCV":["LEG_39777"],"MIIO_MPC":["LEG_39778"],"MIIO_MCOA":["LEG_75987","LEG_1459","LEG_81541"],"MIIO_MTCP":["LEG_39779"],"MIIO_NYDL":["LEG_39780"],"MIIO_VASP":["LEG_39703","LEG_1465","LEG_581"],"MIIO_MGIO":["LEG_75987","LEG_1465","LEG_81678"],"MIIO_MUAC":["LEG_39703","LEG_1456","LEG_583"],"MIIO_QTRL":["LEG_39703","LEG_1461","LEG_843"],"MIIO_DBJV":["LEG_39781"],"MIIO_YCOK":["LEG_39703","LEG_1461","LEG_844"],"MIIO_MTCR":["LEG_39703","LEG_1461","LEG_845"],"MIIO_XLQJ":["LEG_39703","LEG_1459","LEG_846"],"MIIO_MCCC":["LEG_75987","LEG_1461","LEG_81468"],"MIIO_YOCB":["LEG_39703","LEG_1465","LEG_588"],"MIIO_WGGT":["LEG_39703","LEG_1461","LEG_849"],"MIIO_MCOC":["LEG_75987","LEG_1465","LEG_81547"],"MIIO_JFLI":["LEG_75987","LEG_1461","LEG_80439"],"MIIO_MBCO":["LEG_75987","LEG_1461","LEG_81442"],"MIIO_MDCP":["LEG_39782"],"MIIO_GIWF":["LEG_39783"],"MIIO_WPEP":["LEG_39784"],"MIIO_WDXW":["LEG_39703","LEG_1461","LEG_855"],"MIIO_MTCA":["LEG_39785"],"MIIO_MWWC":["LEG_39703","LEG_1461","LEG_857"],"MIIO_MAKA":["LEG_75987","LEG_1465","LEG_81339"],"MIIO_HIKB":["LEG_75987","LEG_1465","LEG_80082"],"MIIO_MSCO":["LEG_39703","LEG_1459","LEG_861"],"MIIO_MCOT":["LEG_75987","LEG_1459","LEG_81561"],"MIIO_AHPE":["LEG_39786"],"MIIO_BECF":["LEG_75987","LEG_1459","LEG_77364"],"MIIO_MCOS":["LEG_75987","LEG_1459","LEG_81554"],"MIIO_SVBW":["LEG_39703","LEG_1456","LEG_597"],"MIIO_UKSD":["LEG_39787"],"MIIO_MCM":["LEG_75987","LEG_1461","LEG_81532"],"MIIO_MICP":["LEG_39788"],"MIIO_SSLJ":["LEG_39703","LEG_1459","LEG_868"],"MIIO_RPIU":["LEG_39789"],"MIIO_MTCO":["LEG_39703","LEG_1459","LEG_869"],"MIIO_YVQG":["LEG_39703","LEG_1465","LEG_599"],"MIIO_LXAJ":["LEG_75987","LEG_1465","LEG_81309"],"MIIO_MARM":["LEG_75987","LEG_1461","LEG_81394"],"MIIO_MOCO":["LEG_39703","LEG_1461","LEG_874"],"MIIO_NGCK":["LEG_39703","LEG_1461","LEG_875"],"MIIO_NCM":["LEG_39703","LEG_1465","LEG_604"],"MIIO_NBSK":["LEG_39790"],"MIIO_NIOM":["LEG_39791"],"MIIO_NAAS":["LEG_39792"],"MIIO_NCOT":["LEG_39793"],"MIIO_YBKE":["LEG_39703","LEG_1459","LEG_879"],"MIIO_NESA":["LEG_39794"],"MIIO_OMYK":["LEG_39795"],"MIIO_NMAA":["LEG_39796"],"MIIO_QLBF":["LEG_39797"],"MIIO_NWCM":["LEG_39703","LEG_1465","LEG_605"],"MIIO_JNZP":["LEG_39798"],"MIIO_OCOH":["LEG_39703","LEG_1461","LEG_883"],"MIIO_OCOT":["LEG_39703","LEG_1461","LEG_884"],"MIIO_OSOH":["LEG_39703","LEG_1461","LEG_885"],"MIIO_PVSC":["LEG_39703","LEG_1461","LEG_886"],"MIIO_PMST":["LEG_39703","LEG_1456","LEG_610"],"MIIO_PPTM":["LEG_39703","LEG_1456","LEG_611"],"MIIO_PMGC":["LEG_39799"],"MIIO_PCOA":["LEG_39800"],"MIIO_PRCP":["LEG_39703","LEG_1461","LEG_889"],"MIIO_PCAA":["LEG_39703","LEG_1461","LEG_890"],"MIIO_PSMO":["LEG_39703","LEG_1456","LEG_614"],"MIIO_PMHT":["LEG_39801"],"MIIO_PNCP":["LEG_39802"],"MIIO_PAAS":["LEG_39803"],"MIIO_PFFE":["LEG_39804"],"MIIO_PVCO":["LEG_39703","LEG_1465","LEG_615"],"MIIO_PASC":["LEG_39703","LEG_1465","LEG_616"],"MIIO_PCOT":["LEG_39703","LEG_1461","LEG_896"],"MIIO_PWCM":["LEG_39703","LEG_1461","LEG_897"],"MIIO_RMSY":["LEG_39703","LEG_1461","LEG_898"],"MIIO_RACK":["LEG_39703","LEG_1459","LEG_899"],"MIIO_RGMG":["LEG_39805"],"MIIO_RCOS":["LEG_39703","LEG_1456","LEG_620"],"MIIO_RUAC":["LEG_75987","LEG_83704","LEG_83672"],"MIIO_WHEU":["LEG_75987","LEG_83704","LEG_83674"],"MIIO_RCOA":["LEG_39806"],"MIIO_SAAS":["LEG_39703","LEG_1459","LEG_903"],"MIIO_SYMR":["LEG_39703","LEG_1461","LEG_904"],"MIIO_SHCF":["LEG_39807"],"MIIO_SKCM":["LEG_39808"],"MIIO_SACP":["LEG_39809"],"MIIO_SCOA":["LEG_39810"],"MIIO_SIOA":["LEG_39703","LEG_1461","LEG_905"],"MIIO_JCLJ":["LEG_39811"],"MIIO_SIOM":["LEG_39812"],"MIIO_SACM":["LEG_39703","LEG_1459","LEG_908"],"MIIO_SEOT":["LEG_39703","LEG_1459","LEG_911"],"MIIO_SIAC":["LEG_39703","LEG_1459","LEG_912"],"MIIO_SDSM":["LEG_39703","LEG_1461","LEG_913"],"MIIO_SMAS":["LEG_39813"],"MIIO_SASC":["LEG_39814"],"MIIO_SODA":["LEG_39815"],"MIIO_MBQF":["LEG_75987","LEG_1461","LEG_81457"],"MIIO_PEMA":["LEG_39816"],"MIIO_MVKH":["LEG_39817"],"MIIO_TASU":["LEG_39703","LEG_1459","LEG_915"],"MIIO_WTSR":["LEG_39818"],"MIIO_SCFW":["LEG_39703","LEG_1456","LEG_627"],"MIIO_QFIP":["LEG_39703","LEG_1459","LEG_918"],"MIIO_SHAS":["LEG_39703","LEG_1459","LEG_919"],"MIIO_SHIO":["LEG_39703","LEG_1459","LEG_920"],"MIIO_SCOT":["LEG_39819"],"MIIO_AEUZ":["LEG_75987","LEG_1461","LEG_76665"],"MIIO_WIUZ":["LEG_39703","LEG_1461","LEG_923"],"MIIO_SGAA":["LEG_39820"],"MIIO_MEWQ":["LEG_75987","LEG_1461","LEG_81674"],"MIIO_SKCT":["LEG_39821"],"MIIO_SNCO":["LEG_39822"],"MIIO_BFMH":["LEG_75987","LEG_1461","LEG_77452"],"MIIO_SNCV":["LEG_39703","LEG_1459","LEG_928"],"MIIO_DLGH":["LEG_75987","LEG_1461","LEG_78800"],"MIIO_YANP":["LEG_39823"],"MIIO_SNCC":["LEG_39703","LEG_1461","LEG_930"],"MIIO_SRVG":["LEG_39824"],"MIIO_SSCE":["LEG_39703","LEG_1465","LEG_634"],"MIIO_SVCK":["LEG_39825"],"MIIO_SVTE":["LEG_39826"],"MIIO_JDNC":["LEG_39827"],"MIIO_SSSS":["LEG_39703","LEG_1459","LEG_937"],"MIIO_SCGC":["LEG_39828"],"MIIO_KSQV":["LEG_75987","LEG_1461","LEG_81121"],"MIIO_SACE":["LEG_39829"],"MIIO_SJCD":["LEG_39703","LEG_1461","LEG_939"],"MIIO_SJCI":["LEG_39830"],"MIIO_SMCS":["LEG_39703","LEG_1461","LEG_941"],"MIIO_STAA":["LEG_39831"],"MIIO_SXAA":["LEG_39703","LEG_1461","LEG_942"],"MIIO_SBCP":["LEG_39703","LEG_1459","LEG_943"],"MIIO_SJAA":["LEG_39832"],"MIIO_SJTC":["LEG_39833"],"MIIO_STTC":["LEG_39703","LEG_1461","LEG_944"],"MIIO_SCT":["LEG_39834"],"MIIO_SACA":["LEG_39703","LEG_1461","LEG_945"],"MIIO_FDJM":["LEG_75987","LEG_1461","LEG_79362"],"MIIO_SSCA":["LEG_39703","LEG_1461","LEG_947"],"MIIO_SACC":["LEG_39703","LEG_1461","LEG_948"],"MIIO_TQJV":["LEG_39703","LEG_1461","LEG_949"],"MIIO_SARB":["LEG_39703","LEG_1461","LEG_950"],"MIIO_TTCN":["LEG_39703","LEG_1459","LEG_951"],"MIIO_TAAC":["LEG_39835"],"MIIO_TAAS":["LEG_39836"],"MIIO_TECO":["LEG_39837"],"MIIO_TMGT":["LEG_39703","LEG_1465","LEG_646"],"MIIO_TECE":["LEG_39838"],"MIIO_UCOA":["LEG_39839"],"MIIO_QNNI":["LEG_39840"],"MIIO_UCFP":["LEG_39703","LEG_1461","LEG_953"],"MIIO_UTEC":["LEG_39841"],"MIIO_QAAW":["LEG_39703","LEG_1461","LEG_954"],"MIIO_ROHW":["LEG_39703","LEG_1456","LEG_649"],"MIIO_BNSK":["LEG_39842"],"MIIO_AIEB":["LEG_39843"],"MIIO_EFYF":["LEG_75987","LEG_1465","LEG_79048"],"MIIO_VPRO":["LEG_39703","LEG_1461","LEG_957"],"MIIO_GBEQ":["LEG_75987","LEG_1459","LEG_79707"],"MIIO_NWSW":["LEG_39844"],"MIIO_GOPO":["LEG_75987","LEG_1461","LEG_79902"],"MIIO_VKHM":["LEG_39703","LEG_1461","LEG_960"],"MIIO_VVCO":["LEG_39845"],"MIIO_VCOA":["LEG_39703","LEG_1461","LEG_962"],"MIIO_VCT":["LEG_39846"],"MIIO_WSCM":["LEG_39703","LEG_1461","LEG_963"],"MIIO_YIOM":["LEG_39847"],"MIIO_ZGCC":["LEG_39703","LEG_1461","LEG_965"]}