{"RCTY_AACV":["LEG_53883"],"RCTY_BYAA":["LEG_53884"],"RCTY_MCBJ":["LEG_53885"],"RCTY_CMKM":["LEG_53886"],"RCTY_CCOG":["LEG_53887"],"RCTY_DPIO":["LEG_53888"],"RCTY_DCFA":["LEG_53889"],"RCTY_EKCC":["LEG_53890"],"RCTY_ECFA":["LEG_53891"],"RCTY_FACD":["LEG_53892"],"RCTY_FBCC":["LEG_53893"],"RCTY_GAAS":["LEG_53894"],"RCTY_GCM":["LEG_53895"],"RCTY_YNGR":["LEG_53896"],"RCTY_GVCO":["LEG_53897"],"RCTY_HGMW":["LEG_53898"],"RCTY_HMCO":["LEG_53899"],"RCTY_IMAA":["LEG_53900"],"RCTY_JNAS":["LEG_53901"],"RCTY_JNTC":["LEG_53902"],"RCTY_JNWA":["LEG_53903"],"RCTY_JIAA":["LEG_53904"],"RCTY_JCOA":["LEG_53905"],"RCTY_FHDX":["LEG_53906"],"RCTY_KAHM":["LEG_53907"],"RCTY_KFAA":["LEG_53908"],"RCTY_EERX":["LEG_53909"],"RCTY_VASP":["LEG_53910"],"RCTY_MGIO":["LEG_53911"],"RCTY_YOCB":["LEG_53912"],"RCTY_MCOC":["LEG_53913"],"RCTY_MAKA":["LEG_53914"],"RCTY_HIKB":["LEG_53915"],"RCTY_YVQG":["LEG_53916"],"RCTY_LXAJ":["LEG_53917"],"RCTY_NCM":["LEG_53918"],"RCTY_NWCM":["LEG_53919"],"RCTY_PVCO":["LEG_53920"],"RCTY_PASC":["LEG_53921"],"RCTY_SSCE":["LEG_53922"],"RCTY_TMGT":["LEG_53923"],"RCTY_EFYF":["LEG_53924"],"RCTY_ALA":["LEG_53925","LEG_1219","LEG_112"],"RCTY_ASM":["LEG_53925","LEG_1220","LEG_114"],"RCTY_CTR":["LEG_53925","LEG_1219","LEG_115"],"RCTY_LFC":["LEG_53925","LEG_1221","LEG_117"],"RCTY_MCY":["LEG_53925","LEG_1219","LEG_118"],"RCTY_MKD":["LEG_53925","LEG_1219","LEG_119"],"RCTY_NAT":["LEG_53925","LEG_1220","LEG_120"],"RCTY_NEM":["LEG_53925","LEG_1219","LEG_121"],"RCTY_OTP":["LEG_53925","LEG_1222","LEG_123"],"RCTY_PRK":["LEG_53925","LEG_1219","LEG_124"],"RCTY_SKG":["LEG_53925","LEG_1221","LEG_125"],"RCTY_SMT":["LEG_53925","LEG_1221","LEG_126"],"RCTY_UOC":["LEG_53926"],"RCTY_VIC":["LEG_53925","LEG_1219","LEG_128"],"RCTY_AHMI":["LEG_53925","LEG_1221","LEG_129"],"RCTY_AHAA":["LEG_53925","LEG_1224","LEG_694"],"RCTY_ACOA":["LEG_53925","LEG_1219","LEG_131"],"RCTY_AAAS":["LEG_53927"],"RCTY_ASOC":["LEG_53925","LEG_1219","LEG_132"],"RCTY_ASOM":["LEG_53925","LEG_1219","LEG_133"],"RCTY_AIAA":["LEG_53928"],"RCTY_AJAA":["LEG_53925","LEG_1222","LEG_134"],"RCTY_ASCO":["LEG_53925","LEG_1222","LEG_135"],"RCTY_AOAC":["LEG_53925","LEG_1219","LEG_136"],"RCTY_AACN":["LEG_53925","LEG_1224","LEG_700"],"RCTY_AACT":["LEG_53929"],"RCTY_QZSP":["LEG_53930"],"RCTY_ACT":["LEG_53931"],"RCTY_FITC":["LEG_53925","LEG_1222","LEG_139"],"RCTY_WCEK":["LEG_53925","LEG_1222","LEG_140"],"RCTY_AAMC":["LEG_53925","LEG_1222","LEG_141"],"RCTY_ATCF":["LEG_53925","LEG_1222","LEG_143"],"RCTY_AWCP":["LEG_53925","LEG_1222","LEG_144"],"RCTY_AIAC":["LEG_53932"],"RCTY_XRLI":["LEG_53933"],"RCTY_AIWA":["LEG_53934"],"RCTY_AIAT":["LEG_53925","LEG_1222","LEG_146"],"RCTY_AIFT":["LEG_53925","LEG_1222","LEG_147"],"RCTY_NMLY":["LEG_53935"],"RCTY_AACP":["LEG_53936"],"RCTY_FWXK":["LEG_53937"],"RCTY_ACOE":["LEG_53938"],"RCTY_ACOS":["LEG_53939"],"RCTY_ASCK":["LEG_53940"],"RCTY_BCC":["LEG_53925","LEG_1224","LEG_717"],"RCTY_BIAC":["LEG_53941"],"RCTY_BIAS":["LEG_53942"],"RCTY_BIOM":["LEG_53925","LEG_1221","LEG_155"],"RCTY_BCOA":["LEG_53925","LEG_1219","LEG_156"],"RCTY_BVNA":["LEG_53925","LEG_1219","LEG_157"],"RCTY_BVNC":["LEG_53925","LEG_1219","LEG_158"],"RCTY_BRIO":["LEG_53943"],"RCTY_BASC":["LEG_53944"],"RCTY_BBTC":["LEG_53925","LEG_1219","LEG_160"],"RCTY_BUAC":["LEG_53925","LEG_1221","LEG_161"],"RCTY_CKRM":["LEG_53945"],"RCTY_CMGC":["LEG_53925","LEG_1224","LEG_724"],"RCTY_CCOA":["LEG_53946"],"RCTY_CURC":["LEG_53925","LEG_1224","LEG_726"],"RCTY_CCM":["LEG_53925","LEG_1221","LEG_164"],"RCTY_CFCS":["LEG_53925","LEG_1219","LEG_165"],"RCTY_MDWG":["LEG_53925","LEG_1221","LEG_166"],"RCTY_BKCS":["LEG_53947"],"RCTY_MPFT":["LEG_53925","LEG_1219","LEG_167"],"RCTY_FNTR":["LEG_53925","LEG_1221","LEG_168"],"RCTY_TEGU":["LEG_53925","LEG_1221","LEG_169"],"RCTY_FIAQ":["LEG_53925","LEG_1221","LEG_170"],"RCTY_UFHJ":["LEG_53925","LEG_1221","LEG_171"],"RCTY_PSUL":["LEG_53925","LEG_1224","LEG_729"],"RCTY_AQYX":["LEG_53948"],"RCTY_ABCD":["LEG_53925","LEG_1221","LEG_175"],"RCTY_CIOR":["LEG_53925","LEG_1219","LEG_177"],"RCTY_CMGM":["LEG_53925","LEG_1219","LEG_178"],"RCTY_CCOS":["LEG_53925","LEG_1222","LEG_179"],"RCTY_CCOM":["LEG_53925","LEG_1221","LEG_180"],"RCTY_CGAA":["LEG_53949"],"RCTY_CCI":["LEG_53925","LEG_1220","LEG_181"],"RCTY_CCOT":["LEG_53950"],"RCTY_CAAS":["LEG_53925","LEG_1224","LEG_734"],"RCTY_COAS":["LEG_53925","LEG_1222","LEG_183"],"RCTY_MWZB":["LEG_53925","LEG_1219","LEG_184"],"RCTY_XGNZ":["LEG_53925","LEG_1219","LEG_185"],"RCTY_PLCT":["LEG_53925","LEG_1224","LEG_736"],"RCTY_JWRH":["LEG_53951"],"RCTY_VVFQ":["LEG_53925","LEG_1221","LEG_187"],"RCTY_FKIA":["LEG_53952"],"RCTY_ZPEB":["LEG_53925","LEG_1219","LEG_188"],"RCTY_YHST":["LEG_53925","LEG_1219","LEG_189"],"RCTY_VPGG":["LEG_53953"],"RCTY_MHFR":["LEG_53925","LEG_1221","LEG_191"],"RCTY_PELD":["LEG_53954"],"RCTY_NOBD":["LEG_53925","LEG_1219","LEG_192"],"RCTY_RLPO":["LEG_53955"],"RCTY_FIEY":["LEG_53956"],"RCTY_CRCF":["LEG_53957"],"RCTY_CCMW":["LEG_53925","LEG_1224","LEG_744"],"RCTY_DMAC":["LEG_53958"],"RCTY_SXMT":["LEG_53959"],"RCTY_DUAC":["LEG_53960"],"RCTY_DUTC":["LEG_53961"],"RCTY_DAAS":["LEG_53962"],"RCTY_DAMC":["LEG_53963"],"RCTY_DCOA":["LEG_53925","LEG_1219","LEG_198"],"RCTY_TXFN":["LEG_53964"],"RCTY_KWHT":["LEG_53925","LEG_1224","LEG_753"],"RCTY_DIOM":["LEG_53925","LEG_1221","LEG_201"],"RCTY_DBCM":["LEG_53965"],"RCTY_JPIH":["LEG_53925","LEG_1221","LEG_202"],"RCTY_DBCS":["LEG_53966"],"RCTY_DPMS":["LEG_53925","LEG_1221","LEG_203"],"RCTY_DAMG":["LEG_53967"],"RCTY_ECOA":["LEG_53968"],"RCTY_EAAS":["LEG_53925","LEG_1224","LEG_759"],"RCTY_EMBC":["LEG_53969"],"RCTY_EIOM":["LEG_53925","LEG_1221","LEG_207"],"RCTY_CCXH":["LEG_53925","LEG_1221","LEG_208"],"RCTY_ETCI":["LEG_53925","LEG_1220","LEG_211"],"RCTY_ETCM":["LEG_53925","LEG_1219","LEG_212"],"RCTY_FCK":["LEG_53970"],"RCTY_FIOM":["LEG_53971"],"RCTY_FTCF":["LEG_53972"],"RCTY_FAAS":["LEG_53925","LEG_1222","LEG_215"],"RCTY_GHAA":["LEG_53973"],"RCTY_GCKK":["LEG_53974"],"RCTY_GASC":["LEG_53925","LEG_1222","LEG_217"],"RCTY_EVZE":["LEG_53975"],"RCTY_CBRK":["LEG_53976"],"RCTY_KAIN":["LEG_53925","LEG_1222","LEG_221"],"RCTY_EKUE":["LEG_53925","LEG_1219","LEG_222"],"RCTY_XOGR":["LEG_53925","LEG_1224","LEG_778"],"RCTY_WUTE":["LEG_53925","LEG_1224","LEG_779"],"RCTY_IODZ":["LEG_53925","LEG_1224","LEG_780"],"RCTY_BMSE":["LEG_53925","LEG_1221","LEG_226"],"RCTY_YRMA":["LEG_53925","LEG_1219","LEG_227"],"RCTY_PCSZ":["LEG_53977"],"RCTY_ALOU":["LEG_53978"],"RCTY_GCOP":["LEG_53979"],"RCTY_GCOT":["LEG_53980"],"RCTY_LYRX":["LEG_53925","LEG_1219","LEG_231"],"RCTY_GCOA":["LEG_53981"],"RCTY_HAAS":["LEG_53925","LEG_1224","LEG_787"],"RCTY_HCOA":["LEG_53925","LEG_1222","LEG_235"],"RCTY_HPKC":["LEG_53925","LEG_1221","LEG_237"],"RCTY_HCIO":["LEG_53982"],"RCTY_HFCO":["LEG_53925","LEG_1219","LEG_238"],"RCTY_HGAO":["LEG_53925","LEG_1221","LEG_239"],"RCTY_XUJC":["LEG_53925","LEG_1221","LEG_240"],"RCTY_IAAS":["LEG_53925","LEG_1222","LEG_241"],"RCTY_ICFA":["LEG_53983"],"RCTY_ICOA":["LEG_53925","LEG_1224","LEG_792"],"RCTY_ITCP":["LEG_53925","LEG_1222","LEG_244"],"RCTY_JTTG":["LEG_53925","LEG_1221","LEG_245"],"RCTY_IASC":["LEG_53984"],"RCTY_LKLX":["LEG_53925","LEG_1222","LEG_247"],"RCTY_IMTT":["LEG_53925","LEG_1219","LEG_248"],"RCTY_IOAS":["LEG_53925","LEG_1221","LEG_249"],"RCTY_IIAC":["LEG_53985"],"RCTY_XHDK":["LEG_53925","LEG_1222","LEG_251"],"RCTY_ICOT":["LEG_53925","LEG_1222","LEG_252"],"RCTY_ICSB":["LEG_53986"],"RCTY_JWAC":["LEG_53987"],"RCTY_JAAS":["LEG_53988"],"RCTY_JICO":["LEG_53989"],"RCTY_JTCM":["LEG_53925","LEG_1221","LEG_257"],"RCTY_JTCK":["LEG_53925","LEG_1221","LEG_259"],"RCTY_KMCO":["LEG_53990"],"RCTY_KTMC":["LEG_53925","LEG_1222","LEG_260"],"RCTY_KPX":["LEG_53925","LEG_1221","LEG_261"],"RCTY_KACT":["LEG_53991"],"RCTY_KSCK":["LEG_53992"],"RCTY_KUMD":["LEG_53993"],"RCTY_KASC":["LEG_53925","LEG_1224","LEG_813"],"RCTY_KCAU":["LEG_53994"],"RCTY_KPAT":["LEG_53925","LEG_1221","LEG_265"],"RCTY_KCOT":["LEG_53995"],"RCTY_KCOD":["LEG_53925","LEG_1221","LEG_267"],"RCTY_KAAS":["LEG_53996"],"RCTY_STEJ":["LEG_53997"],"RCTY_KCOE":["LEG_53998"],"RCTY_TMOV":["LEG_53999"],"RCTY_KSNC":["LEG_54000"],"RCTY_VEKH":["LEG_53925","LEG_1222","LEG_273"],"RCTY_QHPR":["LEG_54001"],"RCTY_KGAS":["LEG_54002"],"RCTY_LNAA":["LEG_53925","LEG_1222","LEG_274"],"RCTY_LMDC":["LEG_54003"],"RCTY_LCOA":["LEG_53925","LEG_1302","LEG_277"],"RCTY_LCOM":["LEG_53925","LEG_1219","LEG_278"],"RCTY_LETC":["LEG_53925","LEG_1219","LEG_279"],"RCTY_LFIO":["LEG_54004"],"RCTY_LAAS":["LEG_54005"],"RCTY_MASC":["LEG_54006"],"RCTY_SPGF":["LEG_54007"],"RCTY_MAAS":["LEG_54008"],"RCTY_QFGD":["LEG_53925","LEG_1222","LEG_282"],"RCTY_KNFJ":["LEG_53925","LEG_1302","LEG_283"],"RCTY_MCV":["LEG_53925","LEG_1224","LEG_834"],"RCTY_MKSH":["LEG_53925","LEG_1219","LEG_285"],"RCTY_MKCV":["LEG_54009"],"RCTY_MMC":["LEG_53925","LEG_1222","LEG_287"],"RCTY_MPC":["LEG_54010"],"RCTY_MCOA":["LEG_53925","LEG_1224","LEG_836"],"RCTY_MTCP":["LEG_54011"],"RCTY_MMSN":["LEG_53925","LEG_1222","LEG_291"],"RCTY_FCKE":["LEG_53925","LEG_1222","LEG_292"],"RCTY_NYDL":["LEG_54012"],"RCTY_MUAC":["LEG_54013"],"RCTY_MTCM":["LEG_53925","LEG_1222","LEG_297"],"RCTY_QTRL":["LEG_54014"],"RCTY_DBJV":["LEG_54015"],"RCTY_YCOK":["LEG_54016"],"RCTY_MTCR":["LEG_54017"],"RCTY_XLQJ":["LEG_53925","LEG_1224","LEG_846"],"RCTY_MCCC":["LEG_54018"],"RCTY_WGGT":["LEG_54019"],"RCTY_JFLI":["LEG_54020"],"RCTY_MBCO":["LEG_54021"],"RCTY_MDCP":["LEG_53925","LEG_1221","LEG_302"],"RCTY_MOCP":["LEG_53925","LEG_1222","LEG_303"],"RCTY_MOTC":["LEG_53925","LEG_1222","LEG_304"],"RCTY_GIWF":["LEG_53925","LEG_1219","LEG_305"],"RCTY_WPEP":["LEG_54022"],"RCTY_WDXW":["LEG_54023"],"RCTY_MOCT":["LEG_53925","LEG_1222","LEG_307"],"RCTY_MTCA":["LEG_54024"],"RCTY_MWWC":["LEG_54025"],"RCTY_MCC":["LEG_53925","LEG_1222","LEG_309"],"RCTY_MSCO":["LEG_53925","LEG_1224","LEG_861"],"RCTY_MCOT":["LEG_53925","LEG_1224","LEG_862"],"RCTY_AHPE":["LEG_53925","LEG_1221","LEG_314"],"RCTY_BECF":["LEG_53925","LEG_1224","LEG_863"],"RCTY_MCOS":["LEG_53925","LEG_1224","LEG_864"],"RCTY_SVBW":["LEG_54026"],"RCTY_UKSD":["LEG_54027"],"RCTY_MCM":["LEG_54028"],"RCTY_MIIO":["LEG_53925","LEG_1222","LEG_319"],"RCTY_MICP":["LEG_53925","LEG_1219","LEG_320"],"RCTY_SSLJ":["LEG_53925","LEG_1224","LEG_868"],"RCTY_RPIU":["LEG_53925","LEG_1221","LEG_322"],"RCTY_MTCO":["LEG_53925","LEG_1224","LEG_869"],"RCTY_RCNF":["LEG_53925","LEG_1222","LEG_326"],"RCTY_MARM":["LEG_54029"],"RCTY_MOCO":["LEG_54030"],"RCTY_NGCK":["LEG_54031"],"RCTY_NBSK":["LEG_53925","LEG_1221","LEG_328"],"RCTY_NIOM":["LEG_53925","LEG_1221","LEG_329"],"RCTY_NAAS":["LEG_53925","LEG_1219","LEG_330"],"RCTY_NCOS":["LEG_53925","LEG_1222","LEG_331"],"RCTY_NCOT":["LEG_53925","LEG_1221","LEG_332"],"RCTY_NCOA":["LEG_53925","LEG_1222","LEG_333"],"RCTY_YBKE":["LEG_53925","LEG_1224","LEG_879"],"RCTY_NESA":["LEG_53925","LEG_1221","LEG_335"],"RCTY_OMYK":["LEG_53925","LEG_1221","LEG_336"],"RCTY_NMAA":["LEG_53925","LEG_1219","LEG_337"],"RCTY_QLBF":["LEG_53925","LEG_1221","LEG_338"],"RCTY_JNZP":["LEG_54032"],"RCTY_NTC":["LEG_53925","LEG_1222","LEG_341"],"RCTY_PYDS":["LEG_53925","LEG_1222","LEG_342"],"RCTY_OCOH":["LEG_54033"],"RCTY_OCOT":["LEG_54034"],"RCTY_OSOH":["LEG_54035"],"RCTY_PVSC":["LEG_54036"],"RCTY_PMST":["LEG_54037"],"RCTY_PPTM":["LEG_54038"],"RCTY_PMGC":["LEG_53925","LEG_1221","LEG_345"],"RCTY_PCOA":["LEG_53925","LEG_1221","LEG_346"],"RCTY_PRCP":["LEG_54039"],"RCTY_PCAA":["LEG_54040"],"RCTY_PDLC":["LEG_53925","LEG_1222","LEG_347"],"RCTY_PSMO":["LEG_54041"],"RCTY_PTMG":["LEG_53925","LEG_1222","LEG_349"],"RCTY_PMHT":["LEG_53925","LEG_1221","LEG_350"],"RCTY_PNCP":["LEG_53925","LEG_1221","LEG_351"],"RCTY_PAAS":["LEG_54042"],"RCTY_PFFE":["LEG_53925","LEG_1219","LEG_353"],"RCTY_PCOT":["LEG_54043"],"RCTY_PWCM":["LEG_54044"],"RCTY_RMSY":["LEG_54045"],"RCTY_RACK":["LEG_53925","LEG_1224","LEG_899"],"RCTY_RGMG":["LEG_53925","LEG_1219","LEG_357"],"RCTY_RCOS":["LEG_54046"],"RCTY_RUAC":["LEG_54047"],"RCTY_WHEU":["LEG_54048"],"RCTY_RCOA":["LEG_54049"],"RCTY_SAAS":["LEG_53925","LEG_1224","LEG_903"],"RCTY_SYMR":["LEG_54050"],"RCTY_SHCF":["LEG_53925","LEG_1221","LEG_361"],"RCTY_SKCM":["LEG_53925","LEG_1219","LEG_362"],"RCTY_SACP":["LEG_54051"],"RCTY_SCOA":["LEG_54052"],"RCTY_SIOA":["LEG_54053"],"RCTY_JCLJ":["LEG_53925","LEG_1221","LEG_365"],"RCTY_SIOM":["LEG_53925","LEG_1221","LEG_366"],"RCTY_SPZS":["LEG_53925","LEG_1222","LEG_367"],"RCTY_SACK":["LEG_53925","LEG_1222","LEG_368"],"RCTY_SACM":["LEG_53925","LEG_1224","LEG_908"],"RCTY_SCWK":["LEG_53925","LEG_1222","LEG_370"],"RCTY_STCK":["LEG_53925","LEG_1222","LEG_371"],"RCTY_SEOT":["LEG_53925","LEG_1224","LEG_911"],"RCTY_SIAC":["LEG_53925","LEG_1224","LEG_912"],"RCTY_SDSM":["LEG_54054"],"RCTY_SMAS":["LEG_54055"],"RCTY_SASC":["LEG_53925","LEG_1221","LEG_375"],"RCTY_SODA":["LEG_53925","LEG_1221","LEG_376"],"RCTY_MBQF":["LEG_54056"],"RCTY_PEMA":["LEG_54057"],"RCTY_MVKH":["LEG_53925","LEG_1219","LEG_378"],"RCTY_TASU":["LEG_53925","LEG_1224","LEG_915"],"RCTY_WTSR":["LEG_53925","LEG_1221","LEG_380"],"RCTY_LGNA":["LEG_53925","LEG_1222","LEG_381"],"RCTY_SCFW":["LEG_54058"],"RCTY_QFIP":["LEG_53925","LEG_1224","LEG_918"],"RCTY_SHAS":["LEG_53925","LEG_1224","LEG_919"],"RCTY_SHIO":["LEG_53925","LEG_1224","LEG_920"],"RCTY_SYSS":["LEG_53925","LEG_1222","LEG_386"],"RCTY_SCOT":["LEG_53925","LEG_1219","LEG_387"],"RCTY_AEUZ":["LEG_54059"],"RCTY_WIUZ":["LEG_54060"],"RCTY_SGAA":["LEG_53925","LEG_1221","LEG_388"],"RCTY_MEWQ":["LEG_54061"],"RCTY_SKCT":["LEG_53925","LEG_1221","LEG_389"],"RCTY_SKVB":["LEG_53925","LEG_1222","LEG_390"],"RCTY_SNCO":["LEG_53925","LEG_1219","LEG_391"],"RCTY_BFMH":["LEG_54062"],"RCTY_SFLH":["LEG_53925","LEG_1222","LEG_392"],"RCTY_SNCV":["LEG_53925","LEG_1224","LEG_928"],"RCTY_DLGH":["LEG_54063"],"RCTY_YANP":["LEG_53925","LEG_1221","LEG_394"],"RCTY_SNCC":["LEG_54064"],"RCTY_SNGS":["LEG_53925","LEG_1302","LEG_395"],"RCTY_SRVG":["LEG_53925","LEG_1219","LEG_396"],"RCTY_SSVC":["LEG_53925","LEG_1222","LEG_398"],"RCTY_SVCO":["LEG_53925","LEG_1222","LEG_399"],"RCTY_SVCK":["LEG_53925","LEG_1221","LEG_400"],"RCTY_SVPK":["LEG_53925","LEG_1222","LEG_401"],"RCTY_SVTE":["LEG_53925","LEG_1221","LEG_402"],"RCTY_SVNC":["LEG_53925","LEG_1222","LEG_403"],"RCTY_JDNC":["LEG_54065"],"RCTY_SSSS":["LEG_53925","LEG_1224","LEG_937"],"RCTY_SCGC":["LEG_53925","LEG_1221","LEG_406"],"RCTY_KSQV":["LEG_54066"],"RCTY_SACE":["LEG_53925","LEG_1221","LEG_407"],"RCTY_SJCD":["LEG_54067"],"RCTY_SJCI":["LEG_53925","LEG_1220","LEG_408"],"RCTY_SMCP":["LEG_53925","LEG_1222","LEG_409"],"RCTY_SMCS":["LEG_54068"],"RCTY_STAA":["LEG_53925","LEG_1221","LEG_410"],"RCTY_SXAA":["LEG_54069"],"RCTY_SBCP":["LEG_53925","LEG_1224","LEG_943"],"RCTY_SJAA":["LEG_53925","LEG_1221","LEG_412"],"RCTY_SJTC":["LEG_53925","LEG_1221","LEG_413"],"RCTY_STTC":["LEG_54070"],"RCTY_SCT":["LEG_53925","LEG_1221","LEG_414"],"RCTY_SACA":["LEG_54071"],"RCTY_FDJM":["LEG_54072"],"RCTY_SSCA":["LEG_54073"],"RCTY_SACC":["LEG_54074"],"RCTY_TQJV":["LEG_54075"],"RCTY_SARB":["LEG_54076"],"RCTY_TTCN":["LEG_53925","LEG_1224","LEG_951"],"RCTY_TAAC":["LEG_54077"],"RCTY_TAAS":["LEG_53925","LEG_1221","LEG_417"],"RCTY_TECO":["LEG_53925","LEG_1219","LEG_418"],"RCTY_TECE":["LEG_53925","LEG_1219","LEG_420"],"RCTY_UCOA":["LEG_53925","LEG_1221","LEG_421"],"RCTY_QNNI":["LEG_53925","LEG_1219","LEG_422"],"RCTY_UCFP":["LEG_54078"],"RCTY_UTEC":["LEG_53925","LEG_1221","LEG_423"],"RCTY_QAAW":["LEG_54079"],"RCTY_ROHW":["LEG_54080"],"RCTY_BNSK":["LEG_53925","LEG_1221","LEG_425"],"RCTY_AIEB":["LEG_53925","LEG_1219","LEG_426"],"RCTY_VPRO":["LEG_54081"],"RCTY_GBEQ":["LEG_53925","LEG_1224","LEG_958"],"RCTY_NWSW":["LEG_53925","LEG_1221","LEG_429"],"RCTY_GOPO":["LEG_54082"],"RCTY_VKHM":["LEG_54083"],"RCTY_VPEC":["LEG_53925","LEG_1222","LEG_430"],"RCTY_VVCO":["LEG_53925","LEG_1219","LEG_431"],"RCTY_VCOA":["LEG_54084"],"RCTY_VCT":["LEG_53925","LEG_1221","LEG_432"],"RCTY_WSCM":["LEG_54085"],"RCTY_WAAS":["LEG_53925","LEG_1222","LEG_433"],"RCTY_YIOM":["LEG_53925","LEG_1219","LEG_434"],"RCTY_ZGCC":["LEG_54086"]}