{"SIOM_ASM":["LEG_358"],"SIOM_LFC":["LEG_582"],"SIOM_NAT":["LEG_894"],"SIOM_SKG":["LEG_1206"],"SIOM_SMT":["LEG_1342"],"SIOM_AHMI":["LEG_1602"],"SIOM_BIOM":["LEG_5808"],"SIOM_BUAC":["LEG_6468"],"SIOM_CCM":["LEG_7132"],"SIOM_MDWG":["LEG_7328"],"SIOM_FNTR":["LEG_7712"],"SIOM_TEGU":["LEG_7836"],"SIOM_FIAQ":["LEG_7956"],"SIOM_UFHJ":["LEG_8074"],"SIOM_ABCD":["LEG_8392"],"SIOM_CCOM":["LEG_8810"],"SIOM_CCI":["LEG_9112"],"SIOM_VVFQ":["LEG_9946"],"SIOM_MHFR":["LEG_10382"],"SIOM_DIOM":["LEG_12374"],"SIOM_JPIH":["LEG_12644"],"SIOM_DPMS":["LEG_12910"],"SIOM_EIOM":["LEG_13488"],"SIOM_CCXH":["LEG_13586"],"SIOM_ETCI":["LEG_13820"],"SIOM_BMSE":["LEG_15700"],"SIOM_HPKC":["LEG_16758"],"SIOM_HGAO":["LEG_17030"],"SIOM_XUJC":["LEG_17118"],"SIOM_JTTG":["LEG_17464"],"SIOM_IOAS":["LEG_17854"],"SIOM_JTCM":["LEG_18814"],"SIOM_JTCK":["LEG_18932"],"SIOM_KPX":["LEG_19212"],"SIOM_KPAT":["LEG_19646"],"SIOM_KCOD":["LEG_19878"],"SIOM_MDCP":["LEG_22870"],"SIOM_AHPE":["LEG_23512"],"SIOM_RPIU":["LEG_23874"],"SIOM_NBSK":["LEG_24302"],"SIOM_NIOM":["LEG_24366"],"SIOM_NCOT":["LEG_24498"],"SIOM_NESA":["LEG_24626"],"SIOM_OMYK":["LEG_24684"],"SIOM_QLBF":["LEG_24766"],"SIOM_PMGC":["LEG_25238"],"SIOM_PCOA":["LEG_25290"],"SIOM_PMHT":["LEG_25550"],"SIOM_PNCP":["LEG_25598"],"SIOM_SHCF":["LEG_26150"],"SIOM_JCLJ":["LEG_26286"],"SIOM_SASC":["LEG_26329"],"SIOM_SODA":["LEG_26331"],"SIOM_WTSR":["LEG_26333"],"SIOM_SGAA":["LEG_26335"],"SIOM_SKCT":["LEG_26337"],"SIOM_YANP":["LEG_26339"],"SIOM_SVCK":["LEG_26341"],"SIOM_SVTE":["LEG_26343"],"SIOM_SCGC":["LEG_26345"],"SIOM_SACE":["LEG_26347"],"SIOM_SJCI":["LEG_26349"],"SIOM_STAA":["LEG_26351"],"SIOM_SJAA":["LEG_26353"],"SIOM_SJTC":["LEG_26355"],"SIOM_SCT":["LEG_26357"],"SIOM_TAAS":["LEG_26359"],"SIOM_UCOA":["LEG_26361"],"SIOM_UTEC":["LEG_26363"],"SIOM_BNSK":["LEG_26365"],"SIOM_NWSW":["LEG_26367"],"SIOM_VCT":["LEG_26369"],"SIOM_ALA":["LEG_28560","LEG_27979","LEG_27980"],"SIOM_CTR":["LEG_28560","LEG_27979","LEG_28943"],"SIOM_MCY":["LEG_28560","LEG_27979","LEG_29186"],"SIOM_MKD":["LEG_28560","LEG_27979","LEG_29302"],"SIOM_NEM":["LEG_28560","LEG_27979","LEG_29533"],"SIOM_OTP":["LEG_29957"],"SIOM_PRK":["LEG_28560","LEG_27979","LEG_30061"],"SIOM_SNGS":["LEG_30393"],"SIOM_UOC":["LEG_28560","LEG_29068","LEG_30697"],"SIOM_VIC":["LEG_28560","LEG_27979","LEG_31183"],"SIOM_AHAA":["LEG_28560","LEG_29059","LEG_27982"],"SIOM_ACOA":["LEG_28560","LEG_27979","LEG_28729"],"SIOM_AAAS":["LEG_28560","LEG_29062","LEG_27986"],"SIOM_ASOC":["LEG_28560","LEG_27979","LEG_28733"],"SIOM_ASOM":["LEG_28560","LEG_27979","LEG_28735"],"SIOM_AIAA":["LEG_28560","LEG_29062","LEG_27989"],"SIOM_AJAA":["LEG_32595"],"SIOM_ASCO":["LEG_32873"],"SIOM_AOAC":["LEG_28560","LEG_27979","LEG_28741"],"SIOM_AACN":["LEG_28560","LEG_29059","LEG_27995"],"SIOM_AACT":["LEG_28560","LEG_29068","LEG_27998"],"SIOM_QZSP":["LEG_28560","LEG_29062","LEG_28001"],"SIOM_ACT":["LEG_28560","LEG_29062","LEG_28003"],"SIOM_FITC":["LEG_34239"],"SIOM_WCEK":["LEG_34515"],"SIOM_AAMC":["LEG_34791"],"SIOM_AACV":["LEG_28560","LEG_29076","LEG_28012"],"SIOM_ATCF":["LEG_35377"],"SIOM_AWCP":["LEG_35653"],"SIOM_AIAC":["LEG_28560","LEG_29062","LEG_28019"],"SIOM_XRLI":["LEG_28560","LEG_29062","LEG_28021"],"SIOM_AIWA":["LEG_28560","LEG_29068","LEG_28023"],"SIOM_AIAT":["LEG_36679"],"SIOM_AIFT":["LEG_36955"],"SIOM_NMLY":["LEG_28560","LEG_29086","LEG_28030"],"SIOM_AACP":["LEG_28560","LEG_29086","LEG_28033"],"SIOM_FWXK":["LEG_28560","LEG_29086","LEG_28035"],"SIOM_ACOE":["LEG_28560","LEG_29062","LEG_28037"],"SIOM_ACOS":["LEG_28560","LEG_29086","LEG_28039"],"SIOM_ASCK":["LEG_28560","LEG_29062","LEG_28041"],"SIOM_BCC":["LEG_28560","LEG_29059","LEG_28043"],"SIOM_BYAA":["LEG_28560","LEG_29076","LEG_28045"],"SIOM_BIAC":["LEG_28560","LEG_29062","LEG_28047"],"SIOM_BIAS":["LEG_28560","LEG_29062","LEG_28049"],"SIOM_BCOA":["LEG_28560","LEG_27979","LEG_28763"],"SIOM_BVNA":["LEG_28560","LEG_27979","LEG_28765"],"SIOM_BVNC":["LEG_28560","LEG_27979","LEG_28767"],"SIOM_BRIO":["LEG_28560","LEG_29062","LEG_28053"],"SIOM_BASC":["LEG_28560","LEG_29068","LEG_28055"],"SIOM_BBTC":["LEG_28560","LEG_27979","LEG_28769"],"SIOM_CKRM":["LEG_28560","LEG_29062","LEG_28059"],"SIOM_CMGC":["LEG_28560","LEG_29059","LEG_28061"],"SIOM_CCOA":["LEG_28560","LEG_29062","LEG_28063"],"SIOM_CURC":["LEG_28560","LEG_29059","LEG_28065"],"SIOM_CFCS":["LEG_28560","LEG_27979","LEG_28771"],"SIOM_BKCS":["LEG_28560","LEG_29062","LEG_28071"],"SIOM_MPFT":["LEG_28560","LEG_27979","LEG_28773"],"SIOM_MCBJ":["LEG_28560","LEG_29076","LEG_28081"],"SIOM_PSUL":["LEG_28560","LEG_29059","LEG_28083"],"SIOM_AQYX":["LEG_28560","LEG_29086","LEG_28085"],"SIOM_CMKM":["LEG_28560","LEG_29076","LEG_28089"],"SIOM_CIOR":["LEG_28560","LEG_27979","LEG_28775"],"SIOM_CMGM":["LEG_28560","LEG_27979","LEG_28777"],"SIOM_CCOS":["LEG_43381"],"SIOM_CGAA":["LEG_28560","LEG_29062","LEG_28095"],"SIOM_CCOT":["LEG_28560","LEG_29062","LEG_28101"],"SIOM_CAAS":["LEG_28560","LEG_29059","LEG_28103"],"SIOM_COAS":["LEG_44346"],"SIOM_MWZB":["LEG_28560","LEG_27979","LEG_28783"],"SIOM_XGNZ":["LEG_28560","LEG_27979","LEG_28785"],"SIOM_PLCT":["LEG_28560","LEG_29059","LEG_28107"],"SIOM_JWRH":["LEG_28560","LEG_29062","LEG_28109"],"SIOM_FKIA":["LEG_28560","LEG_29062","LEG_28113"],"SIOM_ZPEB":["LEG_28560","LEG_27979","LEG_28787"],"SIOM_YHST":["LEG_28560","LEG_27979","LEG_28789"],"SIOM_VPGG":["LEG_28560","LEG_29068","LEG_28115"],"SIOM_PELD":["LEG_28560","LEG_29062","LEG_28119"],"SIOM_NOBD":["LEG_28560","LEG_27979","LEG_28791"],"SIOM_RLPO":["LEG_28560","LEG_29086","LEG_28121"],"SIOM_FIEY":["LEG_28560","LEG_29062","LEG_28123"],"SIOM_CRCF":["LEG_28560","LEG_29062","LEG_28125"],"SIOM_CCOG":["LEG_28560","LEG_29076","LEG_28127"],"SIOM_CCMW":["LEG_28560","LEG_29059","LEG_28129"],"SIOM_DMAC":["LEG_28560","LEG_29062","LEG_28131"],"SIOM_SXMT":["LEG_28560","LEG_29062","LEG_28133"],"SIOM_DUAC":["LEG_28560","LEG_29062","LEG_28135"],"SIOM_DUTC":["LEG_28560","LEG_29062","LEG_28137"],"SIOM_DAAS":["LEG_28560","LEG_29062","LEG_28139"],"SIOM_DPIO":["LEG_28560","LEG_29076","LEG_28141"],"SIOM_DAMC":["LEG_28560","LEG_29068","LEG_28143"],"SIOM_DCOA":["LEG_28560","LEG_27979","LEG_28793"],"SIOM_TXFN":["LEG_28560","LEG_29068","LEG_28145"],"SIOM_KWHT":["LEG_28560","LEG_29059","LEG_28147"],"SIOM_DBCM":["LEG_28560","LEG_29062","LEG_28151"],"SIOM_DBCS":["LEG_28560","LEG_29062","LEG_28155"],"SIOM_DAMG":["LEG_28560","LEG_29062","LEG_28159"],"SIOM_DCFA":["LEG_28560","LEG_29076","LEG_28161"],"SIOM_ECOA":["LEG_28560","LEG_29068","LEG_28163"],"SIOM_EAAS":["LEG_28560","LEG_29059","LEG_28165"],"SIOM_EMBC":["LEG_28560","LEG_29062","LEG_28167"],"SIOM_EKCC":["LEG_28560","LEG_29076","LEG_28173"],"SIOM_ECFA":["LEG_28560","LEG_29076","LEG_28175"],"SIOM_ETCM":["LEG_28560","LEG_27979","LEG_28795"],"SIOM_FACD":["LEG_28560","LEG_29076","LEG_28179"],"SIOM_FBCC":["LEG_28560","LEG_29076","LEG_28181"],"SIOM_FCK":["LEG_28560","LEG_29062","LEG_28183"],"SIOM_FIOM":["LEG_28560","LEG_29062","LEG_28185"],"SIOM_FTCF":["LEG_28560","LEG_29062","LEG_28187"],"SIOM_FAAS":["LEG_52491"],"SIOM_GAAS":["LEG_28560","LEG_29076","LEG_28191"],"SIOM_GHAA":["LEG_28560","LEG_29062","LEG_28193"],"SIOM_GCKK":["LEG_28560","LEG_29062","LEG_28195"],"SIOM_GASC":["LEG_53207"],"SIOM_GCM":["LEG_28560","LEG_29076","LEG_28199"],"SIOM_RCTY":["LEG_28560","LEG_29076","LEG_28201"],"SIOM_EVZE":["LEG_28560","LEG_29068","LEG_28203"],"SIOM_CBRK":["LEG_28560","LEG_29062","LEG_28205"],"SIOM_KAIN":["LEG_54249"],"SIOM_EKUE":["LEG_28560","LEG_27979","LEG_28803"],"SIOM_XOGR":["LEG_28560","LEG_29059","LEG_28209"],"SIOM_WUTE":["LEG_28560","LEG_29059","LEG_28211"],"SIOM_IODZ":["LEG_28560","LEG_29059","LEG_28213"],"SIOM_YRMA":["LEG_28560","LEG_27979","LEG_28805"],"SIOM_PCSZ":["LEG_28560","LEG_29086","LEG_28217"],"SIOM_ALOU":["LEG_28560","LEG_29086","LEG_28219"],"SIOM_GCOP":["LEG_28560","LEG_29062","LEG_28221"],"SIOM_GCOT":["LEG_28560","LEG_29062","LEG_28223"],"SIOM_YNGR":["LEG_28560","LEG_29076","LEG_28225"],"SIOM_LYRX":["LEG_28560","LEG_27979","LEG_28807"],"SIOM_GVCO":["LEG_28560","LEG_29076","LEG_28227"],"SIOM_GCOA":["LEG_28560","LEG_29062","LEG_28229"],"SIOM_HGMW":["LEG_28560","LEG_29076","LEG_28231"],"SIOM_HAAS":["LEG_28560","LEG_29059","LEG_28233"],"SIOM_HCOA":["LEG_56727"],"SIOM_HMCO":["LEG_28560","LEG_29076","LEG_28237"],"SIOM_HCIO":["LEG_28560","LEG_29062","LEG_28241"],"SIOM_HFCO":["LEG_28560","LEG_27979","LEG_28811"],"SIOM_IAAS":["LEG_57573"],"SIOM_ICFA":["LEG_28560","LEG_29086","LEG_28249"],"SIOM_ICOA":["LEG_28560","LEG_29059","LEG_28251"],"SIOM_ITCP":["LEG_58041"],"SIOM_IMAA":["LEG_28560","LEG_29076","LEG_28257"],"SIOM_IASC":["LEG_28560","LEG_29062","LEG_28259"],"SIOM_LKLX":["LEG_58619"],"SIOM_IMTT":["LEG_28560","LEG_27979","LEG_28819"],"SIOM_IIAC":["LEG_28560","LEG_29068","LEG_28265"],"SIOM_XHDK":["LEG_59173"],"SIOM_ICOT":["LEG_59341"],"SIOM_ICSB":["LEG_28560","LEG_29062","LEG_28271"],"SIOM_JWAC":["LEG_28560","LEG_29062","LEG_28273"],"SIOM_JNAS":["LEG_28560","LEG_29076","LEG_28275"],"SIOM_JNTC":["LEG_28560","LEG_29076","LEG_28277"],"SIOM_JNWA":["LEG_28560","LEG_29076","LEG_28279"],"SIOM_JIAA":["LEG_28560","LEG_29076","LEG_28281"],"SIOM_JAAS":["LEG_28560","LEG_29062","LEG_28283"],"SIOM_JICO":["LEG_28560","LEG_29062","LEG_28285"],"SIOM_JCOA":["LEG_28560","LEG_29076","LEG_28289"],"SIOM_KMCO":["LEG_28560","LEG_29062","LEG_28293"],"SIOM_KTMC":["LEG_61203"],"SIOM_KACT":["LEG_28560","LEG_29068","LEG_28299"],"SIOM_KSCK":["LEG_28560","LEG_29062","LEG_28301"],"SIOM_KUMD":["LEG_28560","LEG_29086","LEG_28303"],"SIOM_KASC":["LEG_28560","LEG_29059","LEG_28305"],"SIOM_KCAU":["LEG_28560","LEG_29062","LEG_28307"],"SIOM_KCOT":["LEG_28560","LEG_29062","LEG_28311"],"SIOM_FHDX":["LEG_28560","LEG_29076","LEG_28313"],"SIOM_KAAS":["LEG_28560","LEG_29086","LEG_28317"],"SIOM_STEJ":["LEG_28560","LEG_29062","LEG_28319"],"SIOM_KCOE":["LEG_28560","LEG_29062","LEG_28321"],"SIOM_TMOV":["LEG_28560","LEG_29062","LEG_28323"],"SIOM_KAHM":["LEG_28560","LEG_29076","LEG_28325"],"SIOM_KFAA":["LEG_28560","LEG_29076","LEG_28327"],"SIOM_EERX":["LEG_28560","LEG_29076","LEG_28329"],"SIOM_KSNC":["LEG_28560","LEG_29086","LEG_28331"],"SIOM_VEKH":["LEG_63605"],"SIOM_QHPR":["LEG_28560","LEG_29062","LEG_28335"],"SIOM_KGAS":["LEG_28560","LEG_29062","LEG_28337"],"SIOM_LNAA":["LEG_63949"],"SIOM_LMDC":["LEG_28560","LEG_29068","LEG_28341"],"SIOM_LCOA":["LEG_64281"],"SIOM_LCOM":["LEG_28560","LEG_27979","LEG_28833"],"SIOM_LETC":["LEG_28560","LEG_27979","LEG_28835"],"SIOM_LFIO":["LEG_28560","LEG_29062","LEG_28345"],"SIOM_LAAS":["LEG_28560","LEG_29086","LEG_28347"],"SIOM_MASC":["LEG_28560","LEG_29062","LEG_28349"],"SIOM_SPGF":["LEG_28560","LEG_29062","LEG_28351"],"SIOM_MAAS":["LEG_28560","LEG_29086","LEG_28353"],"SIOM_QFGD":["LEG_65063"],"SIOM_KNFJ":["LEG_65207"],"SIOM_MCV":["LEG_28560","LEG_29059","LEG_28359"],"SIOM_MKSH":["LEG_28560","LEG_27979","LEG_28841"],"SIOM_MKCV":["LEG_28560","LEG_29086","LEG_28361"],"SIOM_MMC":["LEG_65623"],"SIOM_MPC":["LEG_28560","LEG_29086","LEG_28365"],"SIOM_MCOA":["LEG_28560","LEG_29059","LEG_28367"],"SIOM_MTCP":["LEG_28560","LEG_29086","LEG_28369"],"SIOM_MMSN":["LEG_66077"],"SIOM_FCKE":["LEG_66213"],"SIOM_NYDL":["LEG_28560","LEG_29086","LEG_28375"],"SIOM_VASP":["LEG_28560","LEG_29076","LEG_28377"],"SIOM_MGIO":["LEG_28560","LEG_29076","LEG_28379"],"SIOM_MUAC":["LEG_28560","LEG_29068","LEG_28381"],"SIOM_MTCM":["LEG_66903"],"SIOM_QTRL":["LEG_28560","LEG_29062","LEG_28385"],"SIOM_DBJV":["LEG_28560","LEG_29086","LEG_28387"],"SIOM_YCOK":["LEG_28560","LEG_29062","LEG_28389"],"SIOM_MTCR":["LEG_28560","LEG_29062","LEG_28391"],"SIOM_XLQJ":["LEG_28560","LEG_29059","LEG_28393"],"SIOM_MCCC":["LEG_28560","LEG_29062","LEG_28395"],"SIOM_YOCB":["LEG_28560","LEG_29076","LEG_28397"],"SIOM_WGGT":["LEG_28560","LEG_29062","LEG_28399"],"SIOM_MCOC":["LEG_28560","LEG_29076","LEG_28401"],"SIOM_JFLI":["LEG_28560","LEG_29062","LEG_28403"],"SIOM_MBCO":["LEG_28560","LEG_29062","LEG_28405"],"SIOM_MOCP":["LEG_68121"],"SIOM_MOTC":["LEG_68251"],"SIOM_GIWF":["LEG_28560","LEG_27979","LEG_28855"],"SIOM_WPEP":["LEG_28560","LEG_29086","LEG_28413"],"SIOM_WDXW":["LEG_28560","LEG_29062","LEG_28415"],"SIOM_MOCT":["LEG_68591"],"SIOM_MTCA":["LEG_28560","LEG_29086","LEG_28419"],"SIOM_MWWC":["LEG_28560","LEG_29062","LEG_28421"],"SIOM_MCC":["LEG_68877"],"SIOM_MAKA":["LEG_28560","LEG_29076","LEG_28425"],"SIOM_HIKB":["LEG_28560","LEG_29076","LEG_28427"],"SIOM_MSCO":["LEG_28560","LEG_29059","LEG_28429"],"SIOM_MCOT":["LEG_28560","LEG_29059","LEG_28431"],"SIOM_BECF":["LEG_28560","LEG_29059","LEG_28435"],"SIOM_MCOS":["LEG_28560","LEG_29059","LEG_28437"],"SIOM_SVBW":["LEG_28560","LEG_29068","LEG_28439"],"SIOM_UKSD":["LEG_28560","LEG_29086","LEG_28441"],"SIOM_MCM":["LEG_28560","LEG_29062","LEG_28443"],"SIOM_MIIO":["LEG_69905"],"SIOM_MICP":["LEG_28560","LEG_27979","LEG_28863"],"SIOM_SSLJ":["LEG_28560","LEG_29059","LEG_28447"],"SIOM_MTCO":["LEG_28560","LEG_29059","LEG_28451"],"SIOM_YVQG":["LEG_28560","LEG_29076","LEG_28453"],"SIOM_LXAJ":["LEG_28560","LEG_29076","LEG_28455"],"SIOM_RCNF":["LEG_70513"],"SIOM_MARM":["LEG_28560","LEG_29062","LEG_28459"],"SIOM_MOCO":["LEG_28560","LEG_29062","LEG_28461"],"SIOM_NGCK":["LEG_28560","LEG_29062","LEG_28463"],"SIOM_NCM":["LEG_28560","LEG_29076","LEG_28465"],"SIOM_NAAS":["LEG_28560","LEG_27979","LEG_28867"],"SIOM_NCOS":["LEG_71027"],"SIOM_NCOA":["LEG_71175"],"SIOM_YBKE":["LEG_28560","LEG_29059","LEG_28477"],"SIOM_NMAA":["LEG_28560","LEG_27979","LEG_28873"],"SIOM_NWCM":["LEG_28560","LEG_29076","LEG_28485"],"SIOM_JNZP":["LEG_28560","LEG_29086","LEG_28487"],"SIOM_NTC":["LEG_71675"],"SIOM_PYDS":["LEG_71773"],"SIOM_OCOH":["LEG_28560","LEG_29062","LEG_28493"],"SIOM_OCOT":["LEG_28560","LEG_29062","LEG_28495"],"SIOM_OSOH":["LEG_28560","LEG_29062","LEG_28497"],"SIOM_PVSC":["LEG_28560","LEG_29062","LEG_28499"],"SIOM_PMST":["LEG_28560","LEG_29068","LEG_28501"],"SIOM_PPTM":["LEG_28560","LEG_29068","LEG_28503"],"SIOM_PRCP":["LEG_28560","LEG_29062","LEG_28509"],"SIOM_PCAA":["LEG_28560","LEG_29062","LEG_28511"],"SIOM_PDLC":["LEG_72423"],"SIOM_PSMO":["LEG_28560","LEG_29068","LEG_28515"],"SIOM_PTMG":["LEG_72611"],"SIOM_PAAS":["LEG_28560","LEG_29086","LEG_28523"],"SIOM_PFFE":["LEG_28560","LEG_27979","LEG_28883"],"SIOM_PVCO":["LEG_28560","LEG_29076","LEG_28525"],"SIOM_PASC":["LEG_28560","LEG_29076","LEG_28527"],"SIOM_PCOT":["LEG_28560","LEG_29062","LEG_28529"],"SIOM_PWCM":["LEG_28560","LEG_29062","LEG_28531"],"SIOM_RMSY":["LEG_28560","LEG_29062","LEG_28533"],"SIOM_RACK":["LEG_28560","LEG_29059","LEG_28535"],"SIOM_RGMG":["LEG_28560","LEG_27979","LEG_28885"],"SIOM_RCOS":["LEG_28560","LEG_29068","LEG_28537"],"SIOM_RUAC":["LEG_28560","LEG_29062","LEG_28539"],"SIOM_WHEU":["LEG_28560","LEG_29062","LEG_28541"],"SIOM_RCOA":["LEG_28560","LEG_29086","LEG_28543"],"SIOM_SAAS":["LEG_28560","LEG_29059","LEG_28545"],"SIOM_SYMR":["LEG_28560","LEG_29062","LEG_28547"],"SIOM_SKCM":["LEG_28560","LEG_27979","LEG_28887"],"SIOM_SACP":["LEG_28560","LEG_29086","LEG_28551"],"SIOM_SCOA":["LEG_28560","LEG_29086","LEG_28553"],"SIOM_SIOA":["LEG_28560","LEG_29062","LEG_28555"],"SIOM_SPZS":["LEG_73696"],"SIOM_SACK":["LEG_73698"],"SIOM_SACM":["LEG_28560","LEG_29059","LEG_28565"],"SIOM_SCWK":["LEG_73700"],"SIOM_STCK":["LEG_73702"],"SIOM_SEOT":["LEG_28560","LEG_29059","LEG_28571"],"SIOM_SIAC":["LEG_28560","LEG_29059","LEG_28573"],"SIOM_SDSM":["LEG_28560","LEG_29062","LEG_28575"],"SIOM_SMAS":["LEG_28560","LEG_29086","LEG_28577"],"SIOM_MBQF":["LEG_28560","LEG_29062","LEG_28583"],"SIOM_PEMA":["LEG_28560","LEG_29086","LEG_28585"],"SIOM_MVKH":["LEG_28560","LEG_27979","LEG_28897"],"SIOM_TASU":["LEG_28560","LEG_29059","LEG_28587"],"SIOM_LGNA":["LEG_73704"],"SIOM_SCFW":["LEG_28560","LEG_29068","LEG_28593"],"SIOM_QFIP":["LEG_28560","LEG_29059","LEG_28595"],"SIOM_SHAS":["LEG_28560","LEG_29059","LEG_28597"],"SIOM_SHIO":["LEG_28560","LEG_29059","LEG_28599"],"SIOM_SYSS":["LEG_73706"],"SIOM_SCOT":["LEG_28560","LEG_27979","LEG_28903"],"SIOM_AEUZ":["LEG_28560","LEG_29062","LEG_28603"],"SIOM_WIUZ":["LEG_28560","LEG_29062","LEG_28605"],"SIOM_MEWQ":["LEG_28560","LEG_29062","LEG_28609"],"SIOM_SKVB":["LEG_73708"],"SIOM_SNCO":["LEG_28560","LEG_27979","LEG_28907"],"SIOM_BFMH":["LEG_28560","LEG_29062","LEG_28615"],"SIOM_SFLH":["LEG_73710"],"SIOM_SNCV":["LEG_28560","LEG_29059","LEG_28619"],"SIOM_DLGH":["LEG_28560","LEG_29062","LEG_28621"],"SIOM_SNCC":["LEG_28560","LEG_29062","LEG_28625"],"SIOM_SRVG":["LEG_28560","LEG_27979","LEG_28911"],"SIOM_SSCE":["LEG_28560","LEG_29076","LEG_28627"],"SIOM_SSVC":["LEG_73712"],"SIOM_SVCO":["LEG_73714"],"SIOM_SVPK":["LEG_73716"],"SIOM_SVNC":["LEG_73718"],"SIOM_JDNC":["LEG_28560","LEG_29086","LEG_28641"],"SIOM_SSSS":["LEG_28560","LEG_29059","LEG_28643"],"SIOM_KSQV":["LEG_28560","LEG_29062","LEG_28647"],"SIOM_SJCD":["LEG_28560","LEG_29178","LEG_28651"],"SIOM_SMCP":["LEG_73720"],"SIOM_SMCS":["LEG_28560","LEG_29062","LEG_28655"],"SIOM_SXAA":["LEG_28560","LEG_29062","LEG_28659"],"SIOM_SBCP":["LEG_28560","LEG_29059","LEG_28661"],"SIOM_STTC":["LEG_28560","LEG_29062","LEG_28667"],"SIOM_SACA":["LEG_28560","LEG_29062","LEG_28671"],"SIOM_FDJM":["LEG_28560","LEG_29062","LEG_28673"],"SIOM_SSCA":["LEG_28560","LEG_29062","LEG_28675"],"SIOM_SACC":["LEG_28560","LEG_29062","LEG_28677"],"SIOM_TQJV":["LEG_28560","LEG_29062","LEG_28679"],"SIOM_SARB":["LEG_28560","LEG_29062","LEG_28681"],"SIOM_TTCN":["LEG_28560","LEG_29059","LEG_28683"],"SIOM_TAAC":["LEG_28560","LEG_29086","LEG_28685"],"SIOM_TECO":["LEG_28560","LEG_27979","LEG_28926"],"SIOM_TMGT":["LEG_28560","LEG_29076","LEG_28689"],"SIOM_TECE":["LEG_28560","LEG_27979","LEG_28928"],"SIOM_QNNI":["LEG_28560","LEG_27979","LEG_28930"],"SIOM_UCFP":["LEG_28560","LEG_29062","LEG_28693"],"SIOM_QAAW":["LEG_28560","LEG_29062","LEG_28697"],"SIOM_ROHW":["LEG_28560","LEG_29068","LEG_28699"],"SIOM_AIEB":["LEG_28560","LEG_27979","LEG_28932"],"SIOM_EFYF":["LEG_28560","LEG_29076","LEG_28703"],"SIOM_VPRO":["LEG_28560","LEG_29062","LEG_28705"],"SIOM_GBEQ":["LEG_28560","LEG_29059","LEG_28707"],"SIOM_GOPO":["LEG_28560","LEG_29062","LEG_28711"],"SIOM_VKHM":["LEG_28560","LEG_29062","LEG_28713"],"SIOM_VPEC":["LEG_73722"],"SIOM_VVCO":["LEG_28560","LEG_27979","LEG_28936"],"SIOM_VCOA":["LEG_28560","LEG_29062","LEG_28717"],"SIOM_WSCM":["LEG_28560","LEG_29062","LEG_28721"],"SIOM_WAAS":["LEG_73724"],"SIOM_YIOM":["LEG_28560","LEG_27979","LEG_28940"],"SIOM_ZGCC":["LEG_28560","LEG_29062","LEG_28725"]}