{"VVCO_ALA":["LEG_70840"],"VVCO_CTR":["LEG_70841"],"VVCO_MCY":["LEG_70842"],"VVCO_MKD":["LEG_70843"],"VVCO_NEM":["LEG_70844"],"VVCO_PRK":["LEG_70845"],"VVCO_VIC":["LEG_70846"],"VVCO_ACOA":["LEG_70847"],"VVCO_ASOC":["LEG_70848"],"VVCO_ASOM":["LEG_70849"],"VVCO_AOAC":["LEG_70850"],"VVCO_BCOA":["LEG_70851"],"VVCO_BVNA":["LEG_70852"],"VVCO_BVNC":["LEG_70853"],"VVCO_BBTC":["LEG_70854"],"VVCO_CFCS":["LEG_70855"],"VVCO_MPFT":["LEG_70856"],"VVCO_CIOR":["LEG_70857"],"VVCO_CMGM":["LEG_70858"],"VVCO_MWZB":["LEG_70859"],"VVCO_XGNZ":["LEG_70860"],"VVCO_ZPEB":["LEG_70861"],"VVCO_YHST":["LEG_70862"],"VVCO_NOBD":["LEG_70863"],"VVCO_DCOA":["LEG_70864"],"VVCO_ETCM":["LEG_70865"],"VVCO_EKUE":["LEG_70866"],"VVCO_YRMA":["LEG_70867"],"VVCO_LYRX":["LEG_70868"],"VVCO_HFCO":["LEG_70869"],"VVCO_IMTT":["LEG_70870"],"VVCO_LCOM":["LEG_70871"],"VVCO_LETC":["LEG_70872"],"VVCO_MKSH":["LEG_70873"],"VVCO_GIWF":["LEG_70874"],"VVCO_MICP":["LEG_70875"],"VVCO_NAAS":["LEG_70876"],"VVCO_NMAA":["LEG_70877"],"VVCO_PFFE":["LEG_70878"],"VVCO_RGMG":["LEG_70879"],"VVCO_SKCM":["LEG_70880"],"VVCO_MVKH":["LEG_70881"],"VVCO_SCOT":["LEG_70882"],"VVCO_SNCO":["LEG_70883"],"VVCO_SRVG":["LEG_70884"],"VVCO_TECO":["LEG_70885"],"VVCO_TECE":["LEG_70886"],"VVCO_QNNI":["LEG_70887"],"VVCO_AIEB":["LEG_70888"],"VVCO_YIOM":["LEG_70889"],"VVCO_ASM":["LEG_70890","LEG_1793","LEG_114"],"VVCO_LFC":["LEG_70890","LEG_1794","LEG_117"],"VVCO_NAT":["LEG_70890","LEG_1793","LEG_120"],"VVCO_OTP":["LEG_70891"],"VVCO_SKG":["LEG_70890","LEG_1794","LEG_125"],"VVCO_SMT":["LEG_70890","LEG_1794","LEG_126"],"VVCO_UOC":["LEG_70890","LEG_1796","LEG_481"],"VVCO_AHMI":["LEG_70890","LEG_1794","LEG_129"],"VVCO_AHAA":["LEG_70890","LEG_1797","LEG_694"],"VVCO_AAAS":["LEG_70890","LEG_1798","LEG_696"],"VVCO_AIAA":["LEG_70890","LEG_1798","LEG_697"],"VVCO_AJAA":["LEG_70892"],"VVCO_ASCO":["LEG_70893"],"VVCO_AACN":["LEG_70890","LEG_1797","LEG_700"],"VVCO_AACT":["LEG_70890","LEG_1796","LEG_484"],"VVCO_QZSP":["LEG_70890","LEG_1798","LEG_702"],"VVCO_ACT":["LEG_70890","LEG_1798","LEG_703"],"VVCO_FITC":["LEG_70894"],"VVCO_WCEK":["LEG_70895"],"VVCO_AAMC":["LEG_70896"],"VVCO_AACV":["LEG_70890","LEG_1804","LEG_488"],"VVCO_ATCF":["LEG_70897"],"VVCO_AWCP":["LEG_70898"],"VVCO_AIAC":["LEG_70890","LEG_1798","LEG_710"],"VVCO_XRLI":["LEG_70890","LEG_1798","LEG_711"],"VVCO_AIWA":["LEG_70890","LEG_1796","LEG_491"],"VVCO_AIAT":["LEG_70899"],"VVCO_AIFT":["LEG_70900"],"VVCO_NMLY":["LEG_70890","LEG_1809","LEG_149"],"VVCO_AACP":["LEG_70890","LEG_1809","LEG_150"],"VVCO_FWXK":["LEG_70890","LEG_1809","LEG_151"],"VVCO_ACOE":["LEG_70890","LEG_1798","LEG_715"],"VVCO_ACOS":["LEG_70890","LEG_1809","LEG_152"],"VVCO_ASCK":["LEG_70890","LEG_1798","LEG_716"],"VVCO_BCC":["LEG_70890","LEG_1797","LEG_717"],"VVCO_BYAA":["LEG_70890","LEG_1804","LEG_495"],"VVCO_BIAC":["LEG_70890","LEG_1798","LEG_719"],"VVCO_BIAS":["LEG_70890","LEG_1798","LEG_720"],"VVCO_BIOM":["LEG_70890","LEG_1794","LEG_155"],"VVCO_BRIO":["LEG_70890","LEG_1798","LEG_721"],"VVCO_BASC":["LEG_70890","LEG_1796","LEG_499"],"VVCO_BUAC":["LEG_70890","LEG_1794","LEG_161"],"VVCO_CKRM":["LEG_70890","LEG_1798","LEG_723"],"VVCO_CMGC":["LEG_70890","LEG_1797","LEG_724"],"VVCO_CCOA":["LEG_70890","LEG_1798","LEG_725"],"VVCO_CURC":["LEG_70890","LEG_1797","LEG_726"],"VVCO_CCM":["LEG_70890","LEG_1794","LEG_164"],"VVCO_MDWG":["LEG_70890","LEG_1794","LEG_166"],"VVCO_BKCS":["LEG_70890","LEG_1798","LEG_727"],"VVCO_FNTR":["LEG_70890","LEG_1794","LEG_168"],"VVCO_TEGU":["LEG_70890","LEG_1794","LEG_169"],"VVCO_FIAQ":["LEG_70890","LEG_1794","LEG_170"],"VVCO_UFHJ":["LEG_70890","LEG_1794","LEG_171"],"VVCO_MCBJ":["LEG_70890","LEG_1804","LEG_503"],"VVCO_PSUL":["LEG_70890","LEG_1797","LEG_729"],"VVCO_AQYX":["LEG_70890","LEG_1809","LEG_174"],"VVCO_ABCD":["LEG_70890","LEG_1794","LEG_175"],"VVCO_CMKM":["LEG_70890","LEG_1804","LEG_504"],"VVCO_CCOS":["LEG_70901"],"VVCO_CCOM":["LEG_70890","LEG_1794","LEG_180"],"VVCO_CGAA":["LEG_70890","LEG_1798","LEG_732"],"VVCO_CCI":["LEG_70890","LEG_1793","LEG_181"],"VVCO_CCOT":["LEG_70890","LEG_1798","LEG_733"],"VVCO_CAAS":["LEG_70890","LEG_1797","LEG_734"],"VVCO_COAS":["LEG_70902"],"VVCO_PLCT":["LEG_70890","LEG_1797","LEG_736"],"VVCO_JWRH":["LEG_70890","LEG_1798","LEG_737"],"VVCO_VVFQ":["LEG_70890","LEG_1794","LEG_187"],"VVCO_FKIA":["LEG_70890","LEG_1798","LEG_738"],"VVCO_VPGG":["LEG_70890","LEG_1796","LEG_509"],"VVCO_MHFR":["LEG_70890","LEG_1794","LEG_191"],"VVCO_PELD":["LEG_70890","LEG_1798","LEG_740"],"VVCO_RLPO":["LEG_70890","LEG_1809","LEG_193"],"VVCO_FIEY":["LEG_70890","LEG_1798","LEG_741"],"VVCO_CRCF":["LEG_70890","LEG_1798","LEG_742"],"VVCO_CCOG":["LEG_70890","LEG_1804","LEG_513"],"VVCO_CCMW":["LEG_70890","LEG_1797","LEG_744"],"VVCO_DMAC":["LEG_70890","LEG_1798","LEG_745"],"VVCO_SXMT":["LEG_70890","LEG_1798","LEG_746"],"VVCO_DUAC":["LEG_70890","LEG_1798","LEG_747"],"VVCO_DUTC":["LEG_70890","LEG_1798","LEG_748"],"VVCO_DAAS":["LEG_70890","LEG_1798","LEG_749"],"VVCO_DPIO":["LEG_70890","LEG_1804","LEG_519"],"VVCO_DAMC":["LEG_70890","LEG_1796","LEG_520"],"VVCO_TXFN":["LEG_70890","LEG_1796","LEG_521"],"VVCO_KWHT":["LEG_70890","LEG_1797","LEG_753"],"VVCO_DIOM":["LEG_70890","LEG_1794","LEG_201"],"VVCO_DBCM":["LEG_70890","LEG_1798","LEG_754"],"VVCO_JPIH":["LEG_70890","LEG_1794","LEG_202"],"VVCO_DBCS":["LEG_70890","LEG_1798","LEG_755"],"VVCO_DPMS":["LEG_70890","LEG_1794","LEG_203"],"VVCO_DAMG":["LEG_70890","LEG_1798","LEG_756"],"VVCO_DCFA":["LEG_70890","LEG_1804","LEG_525"],"VVCO_ECOA":["LEG_70890","LEG_1796","LEG_526"],"VVCO_EAAS":["LEG_70890","LEG_1797","LEG_759"],"VVCO_EMBC":["LEG_70890","LEG_1798","LEG_760"],"VVCO_EIOM":["LEG_70890","LEG_1794","LEG_207"],"VVCO_CCXH":["LEG_70890","LEG_1794","LEG_208"],"VVCO_EKCC":["LEG_70890","LEG_1804","LEG_528"],"VVCO_ECFA":["LEG_70890","LEG_1804","LEG_529"],"VVCO_ETCI":["LEG_70890","LEG_1793","LEG_211"],"VVCO_FACD":["LEG_70890","LEG_1804","LEG_530"],"VVCO_FBCC":["LEG_70890","LEG_1804","LEG_531"],"VVCO_FCK":["LEG_70890","LEG_1798","LEG_765"],"VVCO_FIOM":["LEG_70890","LEG_1798","LEG_766"],"VVCO_FTCF":["LEG_70890","LEG_1798","LEG_767"],"VVCO_FAAS":["LEG_70903"],"VVCO_GAAS":["LEG_70890","LEG_1804","LEG_535"],"VVCO_GHAA":["LEG_70890","LEG_1798","LEG_770"],"VVCO_GCKK":["LEG_70890","LEG_1798","LEG_771"],"VVCO_GASC":["LEG_70904"],"VVCO_GCM":["LEG_70890","LEG_1804","LEG_538"],"VVCO_RCTY":["LEG_70890","LEG_1804","LEG_539"],"VVCO_EVZE":["LEG_70890","LEG_1796","LEG_540"],"VVCO_CBRK":["LEG_70890","LEG_1798","LEG_776"],"VVCO_KAIN":["LEG_70905"],"VVCO_XOGR":["LEG_70890","LEG_1797","LEG_778"],"VVCO_WUTE":["LEG_70890","LEG_1797","LEG_779"],"VVCO_IODZ":["LEG_70890","LEG_1797","LEG_780"],"VVCO_BMSE":["LEG_70890","LEG_1794","LEG_226"],"VVCO_PCSZ":["LEG_70890","LEG_1809","LEG_228"],"VVCO_ALOU":["LEG_70890","LEG_1809","LEG_229"],"VVCO_GCOP":["LEG_70890","LEG_1798","LEG_781"],"VVCO_GCOT":["LEG_70890","LEG_1798","LEG_782"],"VVCO_YNGR":["LEG_70890","LEG_1804","LEG_544"],"VVCO_GVCO":["LEG_70890","LEG_1804","LEG_545"],"VVCO_GCOA":["LEG_70890","LEG_1798","LEG_785"],"VVCO_HGMW":["LEG_70890","LEG_1804","LEG_547"],"VVCO_HAAS":["LEG_70890","LEG_1797","LEG_787"],"VVCO_HCOA":["LEG_70906"],"VVCO_HMCO":["LEG_70890","LEG_1804","LEG_548"],"VVCO_HPKC":["LEG_70890","LEG_1794","LEG_237"],"VVCO_HCIO":["LEG_70890","LEG_1798","LEG_790"],"VVCO_HGAO":["LEG_70890","LEG_1794","LEG_239"],"VVCO_XUJC":["LEG_70890","LEG_1794","LEG_240"],"VVCO_IAAS":["LEG_70907"],"VVCO_ICFA":["LEG_70890","LEG_1809","LEG_242"],"VVCO_ICOA":["LEG_70890","LEG_1797","LEG_792"],"VVCO_ITCP":["LEG_70908"],"VVCO_JTTG":["LEG_70890","LEG_1794","LEG_245"],"VVCO_IMAA":["LEG_70890","LEG_1804","LEG_550"],"VVCO_IASC":["LEG_70890","LEG_1798","LEG_795"],"VVCO_LKLX":["LEG_70909"],"VVCO_IOAS":["LEG_70890","LEG_1794","LEG_249"],"VVCO_IIAC":["LEG_70890","LEG_1796","LEG_552"],"VVCO_XHDK":["LEG_70910"],"VVCO_ICOT":["LEG_70911"],"VVCO_ICSB":["LEG_70890","LEG_1798","LEG_800"],"VVCO_JWAC":["LEG_70890","LEG_1798","LEG_801"],"VVCO_JNAS":["LEG_70890","LEG_1804","LEG_555"],"VVCO_JNTC":["LEG_70890","LEG_1804","LEG_556"],"VVCO_JNWA":["LEG_70890","LEG_1804","LEG_557"],"VVCO_JIAA":["LEG_70890","LEG_1804","LEG_558"],"VVCO_JAAS":["LEG_70890","LEG_1798","LEG_806"],"VVCO_JICO":["LEG_70890","LEG_1798","LEG_807"],"VVCO_JTCM":["LEG_70890","LEG_1794","LEG_257"],"VVCO_JCOA":["LEG_70890","LEG_1804","LEG_561"],"VVCO_JTCK":["LEG_70890","LEG_1794","LEG_259"],"VVCO_KMCO":["LEG_70890","LEG_1798","LEG_809"],"VVCO_KTMC":["LEG_70912"],"VVCO_KPX":["LEG_70890","LEG_1794","LEG_261"],"VVCO_KACT":["LEG_70890","LEG_1796","LEG_563"],"VVCO_KSCK":["LEG_70890","LEG_1798","LEG_812"],"VVCO_KUMD":["LEG_70890","LEG_1809","LEG_263"],"VVCO_KASC":["LEG_70890","LEG_1797","LEG_813"],"VVCO_KCAU":["LEG_70890","LEG_1798","LEG_814"],"VVCO_KPAT":["LEG_70890","LEG_1794","LEG_265"],"VVCO_KCOT":["LEG_70890","LEG_1798","LEG_815"],"VVCO_FHDX":["LEG_70890","LEG_1804","LEG_567"],"VVCO_KCOD":["LEG_70890","LEG_1794","LEG_267"],"VVCO_KAAS":["LEG_70890","LEG_1809","LEG_268"],"VVCO_STEJ":["LEG_70890","LEG_1798","LEG_817"],"VVCO_KCOE":["LEG_70890","LEG_1798","LEG_818"],"VVCO_TMOV":["LEG_70890","LEG_1798","LEG_819"],"VVCO_KAHM":["LEG_70890","LEG_1804","LEG_571"],"VVCO_KFAA":["LEG_70890","LEG_1804","LEG_572"],"VVCO_EERX":["LEG_70890","LEG_1804","LEG_573"],"VVCO_KSNC":["LEG_70890","LEG_1809","LEG_272"],"VVCO_VEKH":["LEG_70913"],"VVCO_QHPR":["LEG_70890","LEG_1798","LEG_824"],"VVCO_KGAS":["LEG_70890","LEG_1798","LEG_825"],"VVCO_LNAA":["LEG_70914"],"VVCO_LMDC":["LEG_70890","LEG_1796","LEG_576"],"VVCO_LCOA":["LEG_70915"],"VVCO_LFIO":["LEG_70890","LEG_1798","LEG_829"],"VVCO_LAAS":["LEG_70890","LEG_1809","LEG_280"],"VVCO_MASC":["LEG_70890","LEG_1798","LEG_830"],"VVCO_SPGF":["LEG_70890","LEG_1798","LEG_831"],"VVCO_MAAS":["LEG_70890","LEG_1809","LEG_281"],"VVCO_QFGD":["LEG_70916"],"VVCO_KNFJ":["LEG_70917"],"VVCO_MCV":["LEG_70890","LEG_1797","LEG_834"],"VVCO_MKCV":["LEG_70890","LEG_1809","LEG_286"],"VVCO_MMC":["LEG_70918"],"VVCO_MPC":["LEG_70890","LEG_1809","LEG_288"],"VVCO_MCOA":["LEG_70890","LEG_1797","LEG_836"],"VVCO_MTCP":["LEG_70890","LEG_1809","LEG_290"],"VVCO_MMSN":["LEG_70919"],"VVCO_FCKE":["LEG_70920"],"VVCO_NYDL":["LEG_70890","LEG_1809","LEG_293"],"VVCO_VASP":["LEG_70890","LEG_1804","LEG_581"],"VVCO_MGIO":["LEG_70890","LEG_1804","LEG_582"],"VVCO_MUAC":["LEG_70890","LEG_1796","LEG_583"],"VVCO_MTCM":["LEG_70921"],"VVCO_QTRL":["LEG_70890","LEG_1798","LEG_843"],"VVCO_DBJV":["LEG_70890","LEG_1809","LEG_298"],"VVCO_YCOK":["LEG_70890","LEG_1798","LEG_844"],"VVCO_MTCR":["LEG_70890","LEG_1798","LEG_845"],"VVCO_XLQJ":["LEG_70890","LEG_1797","LEG_846"],"VVCO_MCCC":["LEG_70890","LEG_1798","LEG_847"],"VVCO_YOCB":["LEG_70890","LEG_1804","LEG_588"],"VVCO_WGGT":["LEG_70890","LEG_1798","LEG_849"],"VVCO_MCOC":["LEG_70890","LEG_1804","LEG_590"],"VVCO_JFLI":["LEG_70890","LEG_1798","LEG_851"],"VVCO_MBCO":["LEG_70890","LEG_1798","LEG_852"],"VVCO_MDCP":["LEG_70890","LEG_1794","LEG_302"],"VVCO_MOCP":["LEG_70922"],"VVCO_MOTC":["LEG_70923"],"VVCO_WPEP":["LEG_70890","LEG_1809","LEG_306"],"VVCO_WDXW":["LEG_70890","LEG_1798","LEG_855"],"VVCO_MOCT":["LEG_70924"],"VVCO_MTCA":["LEG_70890","LEG_1809","LEG_308"],"VVCO_MWWC":["LEG_70890","LEG_1798","LEG_857"],"VVCO_MCC":["LEG_70925"],"VVCO_MAKA":["LEG_70890","LEG_1804","LEG_595"],"VVCO_HIKB":["LEG_70890","LEG_1804","LEG_596"],"VVCO_MSCO":["LEG_70890","LEG_1797","LEG_861"],"VVCO_MCOT":["LEG_70890","LEG_1797","LEG_862"],"VVCO_AHPE":["LEG_70890","LEG_1794","LEG_314"],"VVCO_BECF":["LEG_70890","LEG_1797","LEG_863"],"VVCO_MCOS":["LEG_70890","LEG_1797","LEG_864"],"VVCO_SVBW":["LEG_70890","LEG_1796","LEG_597"],"VVCO_UKSD":["LEG_70890","LEG_1809","LEG_318"],"VVCO_MCM":["LEG_70890","LEG_1798","LEG_866"],"VVCO_MIIO":["LEG_70926"],"VVCO_SSLJ":["LEG_70890","LEG_1797","LEG_868"],"VVCO_RPIU":["LEG_70890","LEG_1794","LEG_322"],"VVCO_MTCO":["LEG_70890","LEG_1797","LEG_869"],"VVCO_YVQG":["LEG_70890","LEG_1804","LEG_599"],"VVCO_LXAJ":["LEG_70890","LEG_1804","LEG_600"],"VVCO_RCNF":["LEG_70927"],"VVCO_MARM":["LEG_70890","LEG_1798","LEG_873"],"VVCO_MOCO":["LEG_70890","LEG_1798","LEG_874"],"VVCO_NGCK":["LEG_70890","LEG_1798","LEG_875"],"VVCO_NCM":["LEG_70890","LEG_1804","LEG_604"],"VVCO_NBSK":["LEG_70890","LEG_1794","LEG_328"],"VVCO_NIOM":["LEG_70890","LEG_1794","LEG_329"],"VVCO_NCOS":["LEG_70928"],"VVCO_NCOT":["LEG_70890","LEG_1794","LEG_332"],"VVCO_NCOA":["LEG_70929"],"VVCO_YBKE":["LEG_70890","LEG_1797","LEG_879"],"VVCO_NESA":["LEG_70890","LEG_1794","LEG_335"],"VVCO_OMYK":["LEG_70890","LEG_1794","LEG_336"],"VVCO_QLBF":["LEG_70890","LEG_1794","LEG_338"],"VVCO_NWCM":["LEG_70890","LEG_1804","LEG_605"],"VVCO_JNZP":["LEG_70890","LEG_1809","LEG_340"],"VVCO_NTC":["LEG_70930"],"VVCO_PYDS":["LEG_70931"],"VVCO_OCOH":["LEG_70890","LEG_1798","LEG_883"],"VVCO_OCOT":["LEG_70890","LEG_1798","LEG_884"],"VVCO_OSOH":["LEG_70890","LEG_1798","LEG_885"],"VVCO_PVSC":["LEG_70890","LEG_1798","LEG_886"],"VVCO_PMST":["LEG_70890","LEG_1796","LEG_610"],"VVCO_PPTM":["LEG_70890","LEG_1796","LEG_611"],"VVCO_PMGC":["LEG_70890","LEG_1794","LEG_345"],"VVCO_PCOA":["LEG_70890","LEG_1794","LEG_346"],"VVCO_PRCP":["LEG_70890","LEG_1798","LEG_889"],"VVCO_PCAA":["LEG_70890","LEG_1798","LEG_890"],"VVCO_PDLC":["LEG_70932"],"VVCO_PSMO":["LEG_70890","LEG_1796","LEG_614"],"VVCO_PTMG":["LEG_70933"],"VVCO_PMHT":["LEG_70890","LEG_1794","LEG_350"],"VVCO_PNCP":["LEG_70890","LEG_1794","LEG_351"],"VVCO_PAAS":["LEG_70890","LEG_1809","LEG_352"],"VVCO_PVCO":["LEG_70890","LEG_1804","LEG_615"],"VVCO_PASC":["LEG_70890","LEG_1804","LEG_616"],"VVCO_PCOT":["LEG_70890","LEG_1798","LEG_896"],"VVCO_PWCM":["LEG_70890","LEG_1798","LEG_897"],"VVCO_RMSY":["LEG_70890","LEG_1798","LEG_898"],"VVCO_RACK":["LEG_70890","LEG_1797","LEG_899"],"VVCO_RCOS":["LEG_70890","LEG_1796","LEG_620"],"VVCO_RUAC":["LEG_70890","LEG_1798","LEG_901"],"VVCO_WHEU":["LEG_70890","LEG_1798","LEG_902"],"VVCO_RCOA":["LEG_70890","LEG_1809","LEG_359"],"VVCO_SAAS":["LEG_70890","LEG_1797","LEG_903"],"VVCO_SYMR":["LEG_70890","LEG_1798","LEG_904"],"VVCO_SHCF":["LEG_70890","LEG_1794","LEG_361"],"VVCO_SACP":["LEG_70890","LEG_1809","LEG_363"],"VVCO_SCOA":["LEG_70890","LEG_1809","LEG_364"],"VVCO_SIOA":["LEG_70890","LEG_1798","LEG_905"],"VVCO_JCLJ":["LEG_70890","LEG_1794","LEG_365"],"VVCO_SIOM":["LEG_70890","LEG_1794","LEG_366"],"VVCO_SPZS":["LEG_70934"],"VVCO_SACK":["LEG_70935"],"VVCO_SACM":["LEG_70890","LEG_1797","LEG_908"],"VVCO_SCWK":["LEG_70936"],"VVCO_STCK":["LEG_70937"],"VVCO_SEOT":["LEG_70890","LEG_1797","LEG_911"],"VVCO_SIAC":["LEG_70890","LEG_1797","LEG_912"],"VVCO_SDSM":["LEG_70890","LEG_1798","LEG_913"],"VVCO_SMAS":["LEG_70890","LEG_1809","LEG_374"],"VVCO_SASC":["LEG_70890","LEG_1794","LEG_375"],"VVCO_SODA":["LEG_70890","LEG_1794","LEG_376"],"VVCO_MBQF":["LEG_70890","LEG_1798","LEG_914"],"VVCO_PEMA":["LEG_70890","LEG_1809","LEG_377"],"VVCO_TASU":["LEG_70890","LEG_1797","LEG_915"],"VVCO_WTSR":["LEG_70890","LEG_1794","LEG_380"],"VVCO_LGNA":["LEG_70938"],"VVCO_SCFW":["LEG_70890","LEG_1796","LEG_627"],"VVCO_QFIP":["LEG_70890","LEG_1797","LEG_918"],"VVCO_SHAS":["LEG_70890","LEG_1797","LEG_919"],"VVCO_SHIO":["LEG_70890","LEG_1797","LEG_920"],"VVCO_SYSS":["LEG_70939"],"VVCO_AEUZ":["LEG_70890","LEG_1798","LEG_922"],"VVCO_WIUZ":["LEG_70890","LEG_1798","LEG_923"],"VVCO_SGAA":["LEG_70890","LEG_1794","LEG_388"],"VVCO_MEWQ":["LEG_70890","LEG_1798","LEG_924"],"VVCO_SKCT":["LEG_70890","LEG_1794","LEG_389"],"VVCO_SKVB":["LEG_70940"],"VVCO_BFMH":["LEG_70890","LEG_1798","LEG_926"],"VVCO_SFLH":["LEG_70941"],"VVCO_SNCV":["LEG_70890","LEG_1797","LEG_928"],"VVCO_DLGH":["LEG_70890","LEG_1798","LEG_929"],"VVCO_YANP":["LEG_70890","LEG_1794","LEG_394"],"VVCO_SNCC":["LEG_70890","LEG_1798","LEG_930"],"VVCO_SNGS":["LEG_70942"],"VVCO_SSCE":["LEG_70890","LEG_1804","LEG_634"],"VVCO_SSVC":["LEG_70943"],"VVCO_SVCO":["LEG_70944"],"VVCO_SVCK":["LEG_70890","LEG_1794","LEG_400"],"VVCO_SVPK":["LEG_70945"],"VVCO_SVTE":["LEG_70890","LEG_1794","LEG_402"],"VVCO_SVNC":["LEG_70946"],"VVCO_JDNC":["LEG_70890","LEG_1809","LEG_404"],"VVCO_SSSS":["LEG_70890","LEG_1797","LEG_937"],"VVCO_SCGC":["LEG_70890","LEG_1794","LEG_406"],"VVCO_KSQV":["LEG_70890","LEG_1798","LEG_938"],"VVCO_SACE":["LEG_70890","LEG_1794","LEG_407"],"VVCO_SJCD":["LEG_70890","LEG_1798","LEG_939"],"VVCO_SJCI":["LEG_70890","LEG_1793","LEG_408"],"VVCO_SMCP":["LEG_70947"],"VVCO_SMCS":["LEG_70890","LEG_1798","LEG_941"],"VVCO_STAA":["LEG_70890","LEG_1794","LEG_410"],"VVCO_SXAA":["LEG_70890","LEG_1798","LEG_942"],"VVCO_SBCP":["LEG_70890","LEG_1797","LEG_943"],"VVCO_SJAA":["LEG_70890","LEG_1794","LEG_412"],"VVCO_SJTC":["LEG_70890","LEG_1794","LEG_413"],"VVCO_STTC":["LEG_70890","LEG_1798","LEG_944"],"VVCO_SCT":["LEG_70890","LEG_1794","LEG_414"],"VVCO_SACA":["LEG_70890","LEG_1798","LEG_945"],"VVCO_FDJM":["LEG_70890","LEG_1798","LEG_946"],"VVCO_SSCA":["LEG_70890","LEG_1798","LEG_947"],"VVCO_SACC":["LEG_70890","LEG_1798","LEG_948"],"VVCO_TQJV":["LEG_70890","LEG_1798","LEG_949"],"VVCO_SARB":["LEG_70890","LEG_1798","LEG_950"],"VVCO_TTCN":["LEG_70890","LEG_1797","LEG_951"],"VVCO_TAAC":["LEG_70890","LEG_1809","LEG_416"],"VVCO_TAAS":["LEG_70890","LEG_1794","LEG_417"],"VVCO_TMGT":["LEG_70890","LEG_1804","LEG_646"],"VVCO_UCOA":["LEG_70890","LEG_1794","LEG_421"],"VVCO_UCFP":["LEG_70890","LEG_1798","LEG_953"],"VVCO_UTEC":["LEG_70890","LEG_1794","LEG_423"],"VVCO_QAAW":["LEG_70890","LEG_1798","LEG_954"],"VVCO_ROHW":["LEG_70890","LEG_1796","LEG_649"],"VVCO_BNSK":["LEG_70890","LEG_1794","LEG_425"],"VVCO_EFYF":["LEG_70890","LEG_1804","LEG_650"],"VVCO_VPRO":["LEG_70890","LEG_1798","LEG_957"],"VVCO_GBEQ":["LEG_70890","LEG_1797","LEG_958"],"VVCO_NWSW":["LEG_70890","LEG_1794","LEG_429"],"VVCO_GOPO":["LEG_70890","LEG_1798","LEG_959"],"VVCO_VKHM":["LEG_70890","LEG_1798","LEG_960"],"VVCO_VPEC":["LEG_70948"],"VVCO_VCOA":["LEG_70890","LEG_1798","LEG_962"],"VVCO_VCT":["LEG_70890","LEG_1794","LEG_432"],"VVCO_WSCM":["LEG_70890","LEG_1798","LEG_963"],"VVCO_WAAS":["LEG_70949"],"VVCO_ZGCC":["LEG_70890","LEG_1798","LEG_965"]}